<?xml version="1.0" encoding="UTF-8"?><definitions xmlns="http://www.omg.org/spec/BPMN/20100524/MODEL" xmlns:bpmndi="http://www.omg.org/spec/BPMN/20100524/DI" xmlns:i18n="http://www.omg.org/spec/BPMN/non-normative/extensions/i18n/1.0" xmlns:omgdc="http://www.omg.org/spec/DD/20100524/DC" xmlns:omgdi="http://www.omg.org/spec/DD/20100524/DI" xmlns:signavio="http://www.signavio.com" xmlns:xsi="http://www.w3.org/2001/XMLSchema-instance" exporter="Signavio Process Editor, http://www.signavio.com" exporterVersion="18.8.1" expressionLanguage="http://www.w3.org/TR/XPath" id="sid-7adf59d0-3c29-407a-b120-a7b5f91d1c8a" targetNamespace="http://www.signavio.com" typeLanguage="http://www.w3.org/2001/XMLSchema" xsi:schemaLocation="http://www.omg.org/spec/BPMN/20100524/MODEL http://www.omg.org/spec/BPMN/2.0/20100501/BPMN20.xsd">
   <process id="sid-ddd9b946-b7fd-431a-a86e-7b465bb2b052" isClosed="false" isExecutable="false" processType="None">
      <extensionElements>
         <signavio:signavioDiagramMetaData metaKey="prozessreifegrad" metaValue=""/>
         <signavio:signavioDiagramMetaData metaKey="iso9000ff" metaValue=""/>
         <signavio:signavioDiagramMetaData metaKey="processgoal" metaValue=""/>
         <signavio:signavioDiagramMetaData metaKey="meta-processowner" metaValue=""/>
         <signavio:signavioDiagramMetaData metaKey="revisionid" metaValue="73c0dc6dfda5407c8c6b68b60c40bbd3"/>
      </extensionElements>
      <startEvent id="sid-2317A638-A5D2-4EC3-BE9C-E603A98B6A7F" name="">
         <extensionElements>
            <signavio:signavioMetaData metaKey="bgcolor" metaValue="#ffffff"/>
            <signavio:signavioMetaData metaKey="bordercolor" metaValue="#000000"/>
            <signavio:signavioMetaData metaKey="vorgngerprozesse" metaValue="[]"/>
         </extensionElements>
         <outgoing>sid-F48E8617-4FDE-42AD-B676-E8863D057646</outgoing>
      </startEvent>
      <task completionQuantity="1" id="sid-B8C36DE1-F2FA-43B8-8704-CB24D7F2E1FF" isForCompensation="false" name="ACME AG receives invoices" startQuantity="1">
         <extensionElements>
            <signavio:signavioMetaData metaKey="bgcolor" metaValue="#ffffcc"/>
            <signavio:signavioMetaData metaKey="bordercolor" metaValue="#000000"/>
            <signavio:signavioMetaData metaKey="erteiltfreigabe" metaValue=""/>
            <signavio:signavioMetaData metaKey="meta-risks" metaValue=""/>
            <signavio:signavioMetaData metaKey="wirdkonsultiert" metaValue="[]"/>
            <signavio:signavioMetaData metaKey="externaldocuments" metaValue="[]"/>
            <signavio:signavioMetaData metaKey="wirdinformiert" metaValue="[]"/>
         </extensionElements>
         <incoming>sid-F48E8617-4FDE-42AD-B676-E8863D057646</incoming>
         <outgoing>sid-FFED330A-0D57-4CE2-B13E-0E3292D2B364</outgoing>
      </task>
      <task completionQuantity="1" id="sid-F7E8B18F-EC6C-453D-BACE-4FB6F5D0C295" isForCompensation="false" name="Secretariat performs invoice's visual inspection" startQuantity="1">
         <extensionElements>
            <signavio:signavioMetaData metaKey="bgcolor" metaValue="#ffffcc"/>
            <signavio:signavioMetaData metaKey="bordercolor" metaValue="#000000"/>
            <signavio:signavioMetaData metaKey="erteiltfreigabe" metaValue=""/>
            <signavio:signavioMetaData metaKey="meta-risks" metaValue=""/>
            <signavio:signavioMetaData metaKey="wirdkonsultiert" metaValue="[]"/>
            <signavio:signavioMetaData metaKey="externaldocuments" metaValue="[]"/>
            <signavio:signavioMetaData metaKey="wirdinformiert" metaValue="[]"/>
         </extensionElements>
         <incoming>sid-FFED330A-0D57-4CE2-B13E-0E3292D2B364</incoming>
         <outgoing>sid-E305139C-C162-46AC-8C78-BEC440359105</outgoing>
      </task>
      <task completionQuantity="1" id="sid-64704B6E-960B-4C5A-AF54-3BC1009F9D72" isForCompensation="false" name="Secretariat forwards the invoice to an accounting employee" startQuantity="1">
         <extensionElements>
            <signavio:signavioMetaData metaKey="bgcolor" metaValue="#ffffcc"/>
            <signavio:signavioMetaData metaKey="bordercolor" metaValue="#000000"/>
            <signavio:signavioMetaData metaKey="erteiltfreigabe" metaValue=""/>
            <signavio:signavioMetaData metaKey="meta-risks" metaValue=""/>
            <signavio:signavioMetaData metaKey="wirdkonsultiert" metaValue="[]"/>
            <signavio:signavioMetaData metaKey="externaldocuments" metaValue="[]"/>
            <signavio:signavioMetaData metaKey="wirdinformiert" metaValue="[]"/>
         </extensionElements>
         <incoming>sid-E305139C-C162-46AC-8C78-BEC440359105</incoming>
         <outgoing>sid-C9393AA4-5750-48C0-A207-0B1DAE9DD0F2</outgoing>
      </task>
      <task completionQuantity="1" id="sid-041B38D0-8F0F-4AC5-949C-138B4093A933" isForCompensation="false" name="Accounting employee identifies the charging suppliers" startQuantity="1">
         <extensionElements>
            <signavio:signavioMetaData metaKey="bgcolor" metaValue="#ffffcc"/>
            <signavio:signavioMetaData metaKey="bordercolor" metaValue="#000000"/>
            <signavio:signavioMetaData metaKey="erteiltfreigabe" metaValue=""/>
            <signavio:signavioMetaData metaKey="meta-risks" metaValue=""/>
            <signavio:signavioMetaData metaKey="wirdkonsultiert" metaValue="[]"/>
            <signavio:signavioMetaData metaKey="externaldocuments" metaValue="[]"/>
            <signavio:signavioMetaData metaKey="wirdinformiert" metaValue="[]"/>
         </extensionElements>
         <incoming>sid-C9393AA4-5750-48C0-A207-0B1DAE9DD0F2</incoming>
         <outgoing>sid-F9D455C9-F21B-4A1A-BF41-5E5177E6EA15</outgoing>
      </task>
      <task completionQuantity="1" id="sid-6F1893B5-6DDA-4CA6-A2C8-589FB2D85811" isForCompensation="false" name="Accounting employee creates a new invoice " startQuantity="1">
         <extensionElements>
            <signavio:signavioMetaData metaKey="bgcolor" metaValue="#ffffcc"/>
            <signavio:signavioMetaData metaKey="bordercolor" metaValue="#000000"/>
            <signavio:signavioMetaData metaKey="erteiltfreigabe" metaValue=""/>
            <signavio:signavioMetaData metaKey="meta-risks" metaValue=""/>
            <signavio:signavioMetaData metaKey="wirdkonsultiert" metaValue="[]"/>
            <signavio:signavioMetaData metaKey="externaldocuments" metaValue="[]"/>
            <signavio:signavioMetaData metaKey="wirdinformiert" metaValue="[]"/>
         </extensionElements>
         <incoming>sid-F9D455C9-F21B-4A1A-BF41-5E5177E6EA15</incoming>
         <outgoing>sid-6D656B05-27B8-406F-9D0B-AE44347CF573</outgoing>
      </task>
      <task completionQuantity="1" id="sid-7430FB52-4AFD-4F7E-ABE4-2F2A8A733703" isForCompensation="false" name="Accounting employee checks the invoice items" startQuantity="1">
         <extensionElements>
            <signavio:signavioMetaData metaKey="bgcolor" metaValue="#ffffcc"/>
            <signavio:signavioMetaData metaKey="bordercolor" metaValue="#000000"/>
            <signavio:signavioMetaData metaKey="erteiltfreigabe" metaValue=""/>
            <signavio:signavioMetaData metaKey="meta-risks" metaValue=""/>
            <signavio:signavioMetaData metaKey="wirdkonsultiert" metaValue="[]"/>
            <signavio:signavioMetaData metaKey="externaldocuments" metaValue="[]"/>
            <signavio:signavioMetaData metaKey="wirdinformiert" metaValue="[]"/>
         </extensionElements>
         <incoming>sid-6D656B05-27B8-406F-9D0B-AE44347CF573</incoming>
         <outgoing>sid-A692B072-7DEA-4D05-8DDD-A929F3A6D4E8</outgoing>
      </task>
      <task completionQuantity="1" id="sid-2630F32C-9536-4269-A7CF-561AF28EFB1E" isForCompensation="false" name="Accounting employee notes the  cost center and the cost center managers (docket)" startQuantity="1">
         <extensionElements>
            <signavio:signavioMetaData metaKey="bgcolor" metaValue="#ffffcc"/>
            <signavio:signavioMetaData metaKey="bordercolor" metaValue="#000000"/>
            <signavio:signavioMetaData metaKey="erteiltfreigabe" metaValue=""/>
            <signavio:signavioMetaData metaKey="meta-risks" metaValue=""/>
            <signavio:signavioMetaData metaKey="wirdkonsultiert" metaValue="[]"/>
            <signavio:signavioMetaData metaKey="externaldocuments" metaValue="[]"/>
            <signavio:signavioMetaData metaKey="wirdinformiert" metaValue="[]"/>
         </extensionElements>
         <incoming>sid-A692B072-7DEA-4D05-8DDD-A929F3A6D4E8</incoming>
         <outgoing>sid-51044AB8-126C-424D-9106-DA1C11BC2347</outgoing>
      </task>
      <task completionQuantity="1" id="sid-E6923AF8-3A97-40D7-B21F-3646FECB7AF8" isForCompensation="false" name="Accounting employee  sends the docket and the invoice copy to the  cost center manager" startQuantity="1">
         <extensionElements>
            <signavio:signavioMetaData metaKey="bgcolor" metaValue="#ffffcc"/>
            <signavio:signavioMetaData metaKey="bordercolor" metaValue="#000000"/>
            <signavio:signavioMetaData metaKey="erteiltfreigabe" metaValue=""/>
            <signavio:signavioMetaData metaKey="meta-risks" metaValue=""/>
            <signavio:signavioMetaData metaKey="wirdkonsultiert" metaValue="[]"/>
            <signavio:signavioMetaData metaKey="externaldocuments" metaValue="[]"/>
            <signavio:signavioMetaData metaKey="wirdinformiert" metaValue="[]"/>
         </extensionElements>
         <incoming>sid-618AFD2C-2C33-4C4E-A5FF-EC02C036EA1D</incoming>
         <outgoing>sid-2696C129-64B0-4281-92F2-12B173B2BC2A</outgoing>
      </task>
      <task completionQuantity="1" id="sid-0EC2763A-9201-4614-A920-AAAEAFBE8E2C" isForCompensation="false" name="Cost center manager reviews the content for accuracy" startQuantity="1">
         <extensionElements>
            <signavio:signavioMetaData metaKey="bgcolor" metaValue="#ffffcc"/>
            <signavio:signavioMetaData metaKey="bordercolor" metaValue="#000000"/>
            <signavio:signavioMetaData metaKey="erteiltfreigabe" metaValue=""/>
            <signavio:signavioMetaData metaKey="meta-risks" metaValue=""/>
            <signavio:signavioMetaData metaKey="wirdkonsultiert" metaValue="[]"/>
            <signavio:signavioMetaData metaKey="externaldocuments" metaValue="[]"/>
            <signavio:signavioMetaData metaKey="wirdinformiert" metaValue="[]"/>
         </extensionElements>
         <incoming>sid-A9CA8785-6A01-4F96-95D3-D12C0D7B1AFA</incoming>
         <outgoing>sid-BDA672DD-C24D-42EB-857B-065844723B49</outgoing>
      </task>
      <exclusiveGateway gatewayDirection="Diverging" id="sid-33E456DE-CC4F-4B5A-86E7-559336AB9B89" name="in order?">
         <extensionElements>
            <signavio:signavioMetaData metaKey="bgcolor" metaValue="#ffffff"/>
            <signavio:signavioMetaData metaKey="bordercolor" metaValue="#000000"/>
            <signavio:signavioLabel align="center" bottom="false" left="false" ref="text_name" right="false" top="true" valign="bottom" x="20.0" y="-8.0"/>
         </extensionElements>
         <incoming>sid-BDA672DD-C24D-42EB-857B-065844723B49</incoming>
         <outgoing>sid-F823339F-6F9D-452F-AB0F-4F1C2842E809</outgoing>
         <outgoing>sid-9F5CFF22-3AF6-4E31-9448-4E6DF3EE6076</outgoing>
      </exclusiveGateway>
      <task completionQuantity="1" id="sid-FD45EA49-09D1-4095-BB48-556DB1A75527" isForCompensation="false" name="Cost center manager notes his code one on  the docket (AP)" startQuantity="1">
         <extensionElements>
            <signavio:signavioMetaData metaKey="bgcolor" metaValue="#ffffcc"/>
            <signavio:signavioMetaData metaKey="bordercolor" metaValue="#000000"/>
            <signavio:signavioMetaData metaKey="erteiltfreigabe" metaValue=""/>
            <signavio:signavioMetaData metaKey="meta-risks" metaValue=""/>
            <signavio:signavioMetaData metaKey="wirdkonsultiert" metaValue="[]"/>
            <signavio:signavioMetaData metaKey="externaldocuments" metaValue="[]"/>
            <signavio:signavioMetaData metaKey="wirdinformiert" metaValue="[]"/>
         </extensionElements>
         <incoming>sid-F823339F-6F9D-452F-AB0F-4F1C2842E809</incoming>
         <outgoing>sid-383C569E-4570-4E2A-902E-D4C779A0A947</outgoing>
      </task>
      <task completionQuantity="1" id="sid-DC2969BF-6A80-44FC-B3F6-036C0092F0F7" isForCompensation="false" name="Cost center manager returns the copy of the invoice " startQuantity="1">
         <extensionElements>
            <signavio:signavioMetaData metaKey="bgcolor" metaValue="#ffffcc"/>
            <signavio:signavioMetaData metaKey="bordercolor" metaValue="#000000"/>
            <signavio:signavioMetaData metaKey="erteiltfreigabe" metaValue=""/>
            <signavio:signavioMetaData metaKey="meta-risks" metaValue=""/>
            <signavio:signavioMetaData metaKey="wirdkonsultiert" metaValue="[]"/>
            <signavio:signavioMetaData metaKey="externaldocuments" metaValue="[]"/>
            <signavio:signavioMetaData metaKey="wirdinformiert" metaValue="[]"/>
         </extensionElements>
         <incoming>sid-383C569E-4570-4E2A-902E-D4C779A0A947</incoming>
         <outgoing>sid-C209E9C5-4B18-4C90-AE31-B0F1B35CC5D8</outgoing>
      </task>
      <task completionQuantity="1" id="sid-2A51A6C7-5668-46AD-9EFE-8FFF9B5B3032" isForCompensation="false" name="Pass the copy of the invoice to the next cost center manager" startQuantity="1">
         <extensionElements>
            <signavio:signavioMetaData metaKey="bgcolor" metaValue="#ffffcc"/>
            <signavio:signavioMetaData metaKey="bordercolor" metaValue="#000000"/>
            <signavio:signavioMetaData metaKey="erteiltfreigabe" metaValue=""/>
            <signavio:signavioMetaData metaKey="meta-risks" metaValue=""/>
            <signavio:signavioMetaData metaKey="wirdkonsultiert" metaValue="[]"/>
            <signavio:signavioMetaData metaKey="externaldocuments" metaValue="[]"/>
            <signavio:signavioMetaData metaKey="wirdinformiert" metaValue="[]"/>
         </extensionElements>
         <incoming>sid-6DA08284-BF0F-4A64-B9DB-9859CC72E24B</incoming>
         <outgoing>sid-8B6122D3-1291-4058-8E77-2406986C806C</outgoing>
      </task>
      <task completionQuantity="1" id="sid-8863F885-4FF0-4EFD-8BF3-D5065BA3B824" isForCompensation="false" name="Cost center manager  sends invoice back to accounting" startQuantity="1">
         <extensionElements>
            <signavio:signavioMetaData metaKey="bgcolor" metaValue="#ffffcc"/>
            <signavio:signavioMetaData metaKey="bordercolor" metaValue="#000000"/>
            <signavio:signavioMetaData metaKey="erteiltfreigabe" metaValue=""/>
            <signavio:signavioMetaData metaKey="meta-risks" metaValue=""/>
            <signavio:signavioMetaData metaKey="wirdkonsultiert" metaValue="[]"/>
            <signavio:signavioMetaData metaKey="externaldocuments" metaValue="[]"/>
            <signavio:signavioMetaData metaKey="wirdinformiert" metaValue="[]"/>
         </extensionElements>
         <incoming>sid-A9F39EA9-A50C-4474-8BE6-26745F118C1D</incoming>
         <outgoing>sid-208F6111-F08D-4C49-859C-48E0F4ED269F</outgoing>
      </task>
      <exclusiveGateway gatewayDirection="Diverging" id="sid-854C36B9-7E0D-448A-BC64-DDDC9D5FEFAC" name="all items &#10;correct?">
         <extensionElements>
            <signavio:signavioMetaData metaKey="bgcolor" metaValue="#ffffff"/>
            <signavio:signavioMetaData metaKey="bordercolor" metaValue="#000000"/>
            <signavio:signavioLabel align="center" bottom="true" left="false" ref="text_name" right="false" top="false" x="20.0" y="45.0"/>
         </extensionElements>
         <incoming>sid-C209E9C5-4B18-4C90-AE31-B0F1B35CC5D8</incoming>
         <outgoing>sid-6DA08284-BF0F-4A64-B9DB-9859CC72E24B</outgoing>
         <outgoing>sid-6C9D0FEA-F7F5-46BA-8D6F-D2F234811F3D</outgoing>
      </exclusiveGateway>
      <task completionQuantity="1" id="sid-B59DFB83-2885-419F-ADE9-B5650C3847A5" isForCompensation="false" name="Accounting employee proceedes with the clarification with the vendor" startQuantity="1">
         <extensionElements>
            <signavio:signavioMetaData metaKey="bgcolor" metaValue="#ffffcc"/>
            <signavio:signavioMetaData metaKey="bordercolor" metaValue="#000000"/>
            <signavio:signavioMetaData metaKey="erteiltfreigabe" metaValue=""/>
            <signavio:signavioMetaData metaKey="meta-risks" metaValue=""/>
            <signavio:signavioMetaData metaKey="wirdkonsultiert" metaValue="[]"/>
            <signavio:signavioMetaData metaKey="externaldocuments" metaValue="[]"/>
            <signavio:signavioMetaData metaKey="wirdinformiert" metaValue="[]"/>
         </extensionElements>
         <incoming>sid-208F6111-F08D-4C49-859C-48E0F4ED269F</incoming>
         <outgoing>sid-A5DED093-9F99-4E3D-82F3-1F9F59A84173</outgoing>
      </task>
      <exclusiveGateway gatewayDirection="Diverging" id="sid-BD5CC168-F7DC-42B9-BEBD-A3C1DB7207F9" name="questions?">
         <extensionElements>
            <signavio:signavioMetaData metaKey="bgcolor" metaValue="#ffffff"/>
            <signavio:signavioMetaData metaKey="bordercolor" metaValue="#000000"/>
         </extensionElements>
         <incoming>sid-A5DED093-9F99-4E3D-82F3-1F9F59A84173</incoming>
         <outgoing>sid-4436D6ED-1331-4F0D-9BCF-17443A05E75D</outgoing>
         <outgoing>sid-54792194-1B1C-49C0-8CBB-2F48E882A1EA</outgoing>
      </exclusiveGateway>
      <exclusiveGateway gatewayDirection="Converging" id="sid-D6187B08-80E8-477A-92D6-530FFC6ECC63" name="">
         <extensionElements>
            <signavio:signavioMetaData metaKey="bgcolor" metaValue="#ffffff"/>
            <signavio:signavioMetaData metaKey="bordercolor" metaValue="#000000"/>
         </extensionElements>
         <incoming>sid-4436D6ED-1331-4F0D-9BCF-17443A05E75D</incoming>
         <incoming>sid-32F5661F-AB30-4164-89C9-DB9ED760E090</incoming>
         <outgoing>sid-1D40A4AC-2144-4D89-8E4C-B86C5CEFCB8C</outgoing>
      </exclusiveGateway>
      <task completionQuantity="1" id="sid-5CA16D24-3FD5-4CE3-8D6C-2BBF504EAC4F" isForCompensation="false" name="Accounting employee consults the cost center managers" startQuantity="1">
         <extensionElements>
            <signavio:signavioMetaData metaKey="bgcolor" metaValue="#ffffcc"/>
            <signavio:signavioMetaData metaKey="bordercolor" metaValue="#000000"/>
            <signavio:signavioMetaData metaKey="erteiltfreigabe" metaValue=""/>
            <signavio:signavioMetaData metaKey="meta-risks" metaValue=""/>
            <signavio:signavioMetaData metaKey="wirdkonsultiert" metaValue="[]"/>
            <signavio:signavioMetaData metaKey="externaldocuments" metaValue="[]"/>
            <signavio:signavioMetaData metaKey="wirdinformiert" metaValue="[]"/>
         </extensionElements>
         <incoming>sid-54792194-1B1C-49C0-8CBB-2F48E882A1EA</incoming>
         <outgoing>sid-32F5661F-AB30-4164-89C9-DB9ED760E090</outgoing>
      </task>
      <task completionQuantity="1" id="sid-C57349ED-2135-40D6-89F3-C1DECADAE7DA" isForCompensation="false" name="Accounting employee sends the copy of the invoice to the cost center managers" startQuantity="1">
         <extensionElements>
            <signavio:signavioMetaData metaKey="bgcolor" metaValue="#ffffcc"/>
            <signavio:signavioMetaData metaKey="bordercolor" metaValue="#000000"/>
            <signavio:signavioMetaData metaKey="erteiltfreigabe" metaValue=""/>
            <signavio:signavioMetaData metaKey="meta-risks" metaValue=""/>
            <signavio:signavioMetaData metaKey="wirdkonsultiert" metaValue="[]"/>
            <signavio:signavioMetaData metaKey="externaldocuments" metaValue="[]"/>
            <signavio:signavioMetaData metaKey="wirdinformiert" metaValue="[]"/>
         </extensionElements>
         <incoming>sid-1D40A4AC-2144-4D89-8E4C-B86C5CEFCB8C</incoming>
         <outgoing>sid-155BB5ED-7CAC-4D9F-ABD1-3ED8707BA7CD</outgoing>
      </task>
      <task completionQuantity="1" id="sid-AD9D8B14-AC80-4FD4-9051-EFB6ADDD3214" isForCompensation="false" name=" Accounting employee forwards the copy of the invoice to the commercial manager" startQuantity="1">
         <extensionElements>
            <signavio:signavioMetaData metaKey="bgcolor" metaValue="#ffffcc"/>
            <signavio:signavioMetaData metaKey="bordercolor" metaValue="#000000"/>
            <signavio:signavioMetaData metaKey="erteiltfreigabe" metaValue=""/>
            <signavio:signavioMetaData metaKey="meta-risks" metaValue=""/>
            <signavio:signavioMetaData metaKey="wirdkonsultiert" metaValue="[]"/>
            <signavio:signavioMetaData metaKey="externaldocuments" metaValue="[]"/>
            <signavio:signavioMetaData metaKey="wirdinformiert" metaValue="[]"/>
         </extensionElements>
         <incoming>sid-155BB5ED-7CAC-4D9F-ABD1-3ED8707BA7CD</incoming>
         <outgoing>sid-EC6318FE-D1FD-46D7-B5B7-7CF3DA988808</outgoing>
      </task>
      <task completionQuantity="1" id="sid-8F5F2476-4EA2-495E-9757-899AAFC756FD" isForCompensation="false" name="Commercial manager  makes the commercial audit" startQuantity="1">
         <extensionElements>
            <signavio:signavioMetaData metaKey="bgcolor" metaValue="#ffffcc"/>
            <signavio:signavioMetaData metaKey="bordercolor" metaValue="#000000"/>
            <signavio:signavioMetaData metaKey="erteiltfreigabe" metaValue=""/>
            <signavio:signavioMetaData metaKey="meta-risks" metaValue=""/>
            <signavio:signavioMetaData metaKey="wirdkonsultiert" metaValue="[]"/>
            <signavio:signavioMetaData metaKey="externaldocuments" metaValue="[]"/>
            <signavio:signavioMetaData metaKey="wirdinformiert" metaValue="[]"/>
         </extensionElements>
         <incoming>sid-EC6318FE-D1FD-46D7-B5B7-7CF3DA988808</incoming>
         <outgoing>sid-A800686D-D775-4420-86E7-1E531E2A9542</outgoing>
      </task>
      <task completionQuantity="1" id="sid-1F486EB5-3B17-4480-9C18-69BEE45E0245" isForCompensation="false" name="Commercial manager  issues the approval for payment" startQuantity="1">
         <extensionElements>
            <signavio:signavioMetaData metaKey="bgcolor" metaValue="#ffffcc"/>
            <signavio:signavioMetaData metaKey="bordercolor" metaValue="#000000"/>
            <signavio:signavioMetaData metaKey="erteiltfreigabe" metaValue=""/>
            <signavio:signavioMetaData metaKey="meta-risks" metaValue=""/>
            <signavio:signavioMetaData metaKey="wirdkonsultiert" metaValue="[]"/>
            <signavio:signavioMetaData metaKey="externaldocuments" metaValue="[]"/>
            <signavio:signavioMetaData metaKey="wirdinformiert" metaValue="[]"/>
         </extensionElements>
         <incoming>sid-A800686D-D775-4420-86E7-1E531E2A9542</incoming>
         <outgoing>sid-155C3758-2E71-4A7C-980C-3BF408D1F54A</outgoing>
      </task>
      <exclusiveGateway gatewayDirection="Diverging" id="sid-92EA788D-06A7-4D8E-912A-CED64ECC59D4" name="amount?">
         <extensionElements>
            <signavio:signavioMetaData metaKey="bgcolor" metaValue="#ffffff"/>
            <signavio:signavioMetaData metaKey="bordercolor" metaValue="#000000"/>
            <signavio:signavioLabel align="center" bottom="true" left="false" ref="text_name" right="false" top="false" x="20.0" y="45.0"/>
         </extensionElements>
         <incoming>sid-155C3758-2E71-4A7C-980C-3BF408D1F54A</incoming>
         <outgoing>sid-94A41BA6-5A67-4D8B-BB91-A04237847054</outgoing>
         <outgoing>sid-29674EBC-F2E6-479A-A313-56BE61C7E390</outgoing>
      </exclusiveGateway>
      <task completionQuantity="1" id="sid-AC7992E6-06B8-435D-9F22-60658848E4C2" isForCompensation="false" name="Board checks invoice " startQuantity="1">
         <extensionElements>
            <signavio:signavioMetaData metaKey="bgcolor" metaValue="#ffffcc"/>
            <signavio:signavioMetaData metaKey="bordercolor" metaValue="#000000"/>
            <signavio:signavioMetaData metaKey="erteiltfreigabe" metaValue=""/>
            <signavio:signavioMetaData metaKey="meta-risks" metaValue=""/>
            <signavio:signavioMetaData metaKey="wirdkonsultiert" metaValue="[]"/>
            <signavio:signavioMetaData metaKey="externaldocuments" metaValue="[]"/>
            <signavio:signavioMetaData metaKey="wirdinformiert" metaValue="[]"/>
         </extensionElements>
         <incoming>sid-94A41BA6-5A67-4D8B-BB91-A04237847054</incoming>
         <outgoing>sid-883B2AC1-4FB1-435E-99DC-695C80A6703A</outgoing>
      </task>
      <exclusiveGateway gatewayDirection="Converging" id="sid-C85C7258-8C45-490E-B0BF-C495C637DF62" name="">
         <extensionElements>
            <signavio:signavioMetaData metaKey="bgcolor" metaValue="#ffffff"/>
            <signavio:signavioMetaData metaKey="bordercolor" metaValue="#000000"/>
         </extensionElements>
         <incoming>sid-883B2AC1-4FB1-435E-99DC-695C80A6703A</incoming>
         <incoming>sid-29674EBC-F2E6-479A-A313-56BE61C7E390</incoming>
         <outgoing>sid-7736E86C-8EFF-4509-A98D-0F06EE0498AF</outgoing>
      </exclusiveGateway>
      <task completionQuantity="1" id="sid-677CABCE-CD21-4737-9EB9-FED9D2F9F061" isForCompensation="false" name="Commercial manager moves invoice's copy  and the docket to the accounting employee " startQuantity="1">
         <extensionElements>
            <signavio:signavioMetaData metaKey="bgcolor" metaValue="#ffffcc"/>
            <signavio:signavioMetaData metaKey="bordercolor" metaValue="#000000"/>
            <signavio:signavioMetaData metaKey="erteiltfreigabe" metaValue=""/>
            <signavio:signavioMetaData metaKey="meta-risks" metaValue=""/>
            <signavio:signavioMetaData metaKey="wirdkonsultiert" metaValue="[]"/>
            <signavio:signavioMetaData metaKey="externaldocuments" metaValue="[]"/>
            <signavio:signavioMetaData metaKey="wirdinformiert" metaValue="[]"/>
         </extensionElements>
         <incoming>sid-7736E86C-8EFF-4509-A98D-0F06EE0498AF</incoming>
         <outgoing>sid-B30CA1EE-CF7C-40BA-A05B-A092B857D9E9</outgoing>
      </task>
      <exclusiveGateway gatewayDirection="Diverging" id="sid-435EB1D1-786A-411B-984A-8943524F8FD5" name=" complaint&#10; during the &#10;commercial audit?">
         <extensionElements>
            <signavio:signavioMetaData metaKey="bgcolor" metaValue="#ffffff"/>
            <signavio:signavioMetaData metaKey="bordercolor" metaValue="#000000"/>
            <signavio:signavioLabel align="center" bottom="true" left="false" ref="text_name" right="false" top="false" x="20.0" y="45.0"/>
         </extensionElements>
         <incoming>sid-B30CA1EE-CF7C-40BA-A05B-A092B857D9E9</incoming>
         <outgoing>sid-1975545F-B636-4B1D-9C3D-D659AEFD7541</outgoing>
         <outgoing>sid-FE70F0AD-AA74-41A2-879D-0A6B82B68D35</outgoing>
      </exclusiveGateway>
      <task completionQuantity="1" id="sid-13355D1A-3CAF-4D8B-9411-A88A615733C2" isForCompensation="false" name="Accounting employee resolves complaint" startQuantity="1">
         <extensionElements>
            <signavio:signavioMetaData metaKey="bgcolor" metaValue="#ffffcc"/>
            <signavio:signavioMetaData metaKey="bordercolor" metaValue="#000000"/>
            <signavio:signavioMetaData metaKey="erteiltfreigabe" metaValue=""/>
            <signavio:signavioMetaData metaKey="meta-risks" metaValue=""/>
            <signavio:signavioMetaData metaKey="wirdkonsultiert" metaValue="[]"/>
            <signavio:signavioMetaData metaKey="externaldocuments" metaValue="[]"/>
            <signavio:signavioMetaData metaKey="wirdinformiert" metaValue="[]"/>
         </extensionElements>
         <incoming>sid-FE70F0AD-AA74-41A2-879D-0A6B82B68D35</incoming>
         <outgoing>sid-2FBA0C62-F46C-4967-9F39-AC37E19A3CF4</outgoing>
      </task>
      <exclusiveGateway gatewayDirection="Converging" id="sid-6E780731-665F-4684-B805-446F5BA5C7A1" name="">
         <extensionElements>
            <signavio:signavioMetaData metaKey="bgcolor" metaValue="#ffffff"/>
            <signavio:signavioMetaData metaKey="bordercolor" metaValue="#000000"/>
         </extensionElements>
         <incoming>sid-2FBA0C62-F46C-4967-9F39-AC37E19A3CF4</incoming>
         <incoming>sid-1975545F-B636-4B1D-9C3D-D659AEFD7541</incoming>
         <outgoing>sid-50D7AB66-0E6F-4D1B-8E28-BEDB9264FB21</outgoing>
      </exclusiveGateway>
      <task completionQuantity="1" id="sid-247ED8B9-DDFF-4DFC-A104-AF2CB3692A93" isForCompensation="false" name="Accounting employee gives payment instructions" startQuantity="1">
         <extensionElements>
            <signavio:signavioMetaData metaKey="bgcolor" metaValue="#ffffcc"/>
            <signavio:signavioMetaData metaKey="bordercolor" metaValue="#000000"/>
            <signavio:signavioMetaData metaKey="erteiltfreigabe" metaValue=""/>
            <signavio:signavioMetaData metaKey="meta-risks" metaValue=""/>
            <signavio:signavioMetaData metaKey="wirdkonsultiert" metaValue="[]"/>
            <signavio:signavioMetaData metaKey="externaldocuments" metaValue="[]"/>
            <signavio:signavioMetaData metaKey="wirdinformiert" metaValue="[]"/>
         </extensionElements>
         <incoming>sid-50D7AB66-0E6F-4D1B-8E28-BEDB9264FB21</incoming>
         <outgoing>sid-1BBE3964-B85A-4B0D-AE10-5767BCD9DE10</outgoing>
      </task>
      <task completionQuantity="1" id="sid-62948860-1F23-4957-90B8-9772DFAA3582" isForCompensation="false" name="Accounting employee closes the invoice" startQuantity="1">
         <extensionElements>
            <signavio:signavioMetaData metaKey="bgcolor" metaValue="#ffffcc"/>
            <signavio:signavioMetaData metaKey="bordercolor" metaValue="#000000"/>
            <signavio:signavioMetaData metaKey="erteiltfreigabe" metaValue=""/>
            <signavio:signavioMetaData metaKey="meta-risks" metaValue=""/>
            <signavio:signavioMetaData metaKey="wirdkonsultiert" metaValue="[]"/>
            <signavio:signavioMetaData metaKey="externaldocuments" metaValue="[]"/>
            <signavio:signavioMetaData metaKey="wirdinformiert" metaValue="[]"/>
         </extensionElements>
         <incoming>sid-1BBE3964-B85A-4B0D-AE10-5767BCD9DE10</incoming>
         <outgoing>sid-D99349A7-27DD-4BDC-BBB2-7EC503E56099</outgoing>
      </task>
      <endEvent id="sid-01E3C6E3-CD7A-4DAC-9B9D-AC030EA04370" name="">
         <extensionElements>
            <signavio:signavioMetaData metaKey="bgcolor" metaValue="#ffffff"/>
            <signavio:signavioMetaData metaKey="bordercolor" metaValue="#000000"/>
            <signavio:signavioMetaData metaKey="nachfolgerprozesse" metaValue="[]"/>
         </extensionElements>
         <incoming>sid-D99349A7-27DD-4BDC-BBB2-7EC503E56099</incoming>
      </endEvent>
      <task completionQuantity="1" id="sid-9DFA5417-4FEC-425B-B2D1-B5F03D68678A" isForCompensation="false" name="Docket and the invoice's copy go to the internal mail" startQuantity="1">
         <extensionElements>
            <signavio:signavioMetaData metaKey="bgcolor" metaValue="#ffffcc"/>
            <signavio:signavioMetaData metaKey="bordercolor" metaValue="#000000"/>
            <signavio:signavioMetaData metaKey="erteiltfreigabe" metaValue=""/>
            <signavio:signavioMetaData metaKey="meta-risks" metaValue=""/>
            <signavio:signavioMetaData metaKey="wirdkonsultiert" metaValue="[]"/>
            <signavio:signavioMetaData metaKey="externaldocuments" metaValue="[]"/>
            <signavio:signavioMetaData metaKey="wirdinformiert" metaValue="[]"/>
         </extensionElements>
         <incoming>sid-51044AB8-126C-424D-9106-DA1C11BC2347</incoming>
         <outgoing>sid-618AFD2C-2C33-4C4E-A5FF-EC02C036EA1D</outgoing>
      </task>
      <task completionQuantity="1" id="sid-EDBE25D0-9DBB-4CF1-9E32-2D030C43D7C2" isForCompensation="false" name="Cost center manager receives the copy of the invoice" startQuantity="1">
         <extensionElements>
            <signavio:signavioMetaData metaKey="bgcolor" metaValue="#ffffcc"/>
            <signavio:signavioMetaData metaKey="bordercolor" metaValue="#000000"/>
            <signavio:signavioMetaData metaKey="erteiltfreigabe" metaValue=""/>
            <signavio:signavioMetaData metaKey="meta-risks" metaValue=""/>
            <signavio:signavioMetaData metaKey="wirdkonsultiert" metaValue="[]"/>
            <signavio:signavioMetaData metaKey="externaldocuments" metaValue="[]"/>
            <signavio:signavioMetaData metaKey="wirdinformiert" metaValue="[]"/>
         </extensionElements>
         <incoming>sid-0B5E3CD8-AC7F-43E6-984F-FDD78F0FDA96</incoming>
         <outgoing>sid-A9CA8785-6A01-4F96-95D3-D12C0D7B1AFA</outgoing>
      </task>
      <exclusiveGateway gatewayDirection="Converging" id="sid-418B38FB-7008-44FB-B9CE-120166643831" name="">
         <extensionElements>
            <signavio:signavioMetaData metaKey="bgcolor" metaValue="#ffffff"/>
            <signavio:signavioMetaData metaKey="bordercolor" metaValue="#000000"/>
         </extensionElements>
         <incoming>sid-2696C129-64B0-4281-92F2-12B173B2BC2A</incoming>
         <incoming>sid-8B6122D3-1291-4058-8E77-2406986C806C</incoming>
         <outgoing>sid-0B5E3CD8-AC7F-43E6-984F-FDD78F0FDA96</outgoing>
      </exclusiveGateway>
      <task completionQuantity="1" id="sid-36110983-BA76-479B-A292-384FAF79D0CD" isForCompensation="false" name="Cost center manager rejects the AP " startQuantity="1">
         <extensionElements>
            <signavio:signavioMetaData metaKey="bgcolor" metaValue="#ffffcc"/>
            <signavio:signavioMetaData metaKey="bordercolor" metaValue="#000000"/>
            <signavio:signavioMetaData metaKey="erteiltfreigabe" metaValue=""/>
            <signavio:signavioMetaData metaKey="meta-risks" metaValue=""/>
            <signavio:signavioMetaData metaKey="wirdkonsultiert" metaValue="[]"/>
            <signavio:signavioMetaData metaKey="externaldocuments" metaValue="[]"/>
            <signavio:signavioMetaData metaKey="wirdinformiert" metaValue="[]"/>
         </extensionElements>
         <incoming>sid-9F5CFF22-3AF6-4E31-9448-4E6DF3EE6076</incoming>
         <outgoing>sid-4CC411B5-9071-4F30-A8D1-2389EAE0D1DB</outgoing>
      </task>
      <exclusiveGateway gatewayDirection="Converging" id="sid-AD244CB0-E51D-45BA-ADC9-5B93EE8F48CD" name="">
         <extensionElements>
            <signavio:signavioMetaData metaKey="bgcolor" metaValue="#ffffff"/>
            <signavio:signavioMetaData metaKey="bordercolor" metaValue="#000000"/>
         </extensionElements>
         <incoming>sid-6C9D0FEA-F7F5-46BA-8D6F-D2F234811F3D</incoming>
         <incoming>sid-4CC411B5-9071-4F30-A8D1-2389EAE0D1DB</incoming>
         <outgoing>sid-A9F39EA9-A50C-4474-8BE6-26745F118C1D</outgoing>
      </exclusiveGateway>
      <sequenceFlow id="sid-F48E8617-4FDE-42AD-B676-E8863D057646" name="" sourceRef="sid-2317A638-A5D2-4EC3-BE9C-E603A98B6A7F" targetRef="sid-B8C36DE1-F2FA-43B8-8704-CB24D7F2E1FF">
         <extensionElements>
            <signavio:signavioMetaData metaKey="bordercolor" metaValue="#000000"/>
         </extensionElements>
      </sequenceFlow>
      <sequenceFlow id="sid-FFED330A-0D57-4CE2-B13E-0E3292D2B364" name="" sourceRef="sid-B8C36DE1-F2FA-43B8-8704-CB24D7F2E1FF" targetRef="sid-F7E8B18F-EC6C-453D-BACE-4FB6F5D0C295">
         <extensionElements>
            <signavio:signavioMetaData metaKey="bordercolor" metaValue="#000000"/>
         </extensionElements>
      </sequenceFlow>
      <sequenceFlow id="sid-E305139C-C162-46AC-8C78-BEC440359105" name="" sourceRef="sid-F7E8B18F-EC6C-453D-BACE-4FB6F5D0C295" targetRef="sid-64704B6E-960B-4C5A-AF54-3BC1009F9D72">
         <extensionElements>
            <signavio:signavioMetaData metaKey="bordercolor" metaValue="#000000"/>
         </extensionElements>
      </sequenceFlow>
      <sequenceFlow id="sid-C9393AA4-5750-48C0-A207-0B1DAE9DD0F2" name="" sourceRef="sid-64704B6E-960B-4C5A-AF54-3BC1009F9D72" targetRef="sid-041B38D0-8F0F-4AC5-949C-138B4093A933">
         <extensionElements>
            <signavio:signavioMetaData metaKey="bordercolor" metaValue="#000000"/>
         </extensionElements>
      </sequenceFlow>
      <sequenceFlow id="sid-F9D455C9-F21B-4A1A-BF41-5E5177E6EA15" name="" sourceRef="sid-041B38D0-8F0F-4AC5-949C-138B4093A933" targetRef="sid-6F1893B5-6DDA-4CA6-A2C8-589FB2D85811">
         <extensionElements>
            <signavio:signavioMetaData metaKey="bordercolor" metaValue="#000000"/>
         </extensionElements>
      </sequenceFlow>
      <sequenceFlow id="sid-6D656B05-27B8-406F-9D0B-AE44347CF573" name="" sourceRef="sid-6F1893B5-6DDA-4CA6-A2C8-589FB2D85811" targetRef="sid-7430FB52-4AFD-4F7E-ABE4-2F2A8A733703">
         <extensionElements>
            <signavio:signavioMetaData metaKey="bordercolor" metaValue="#000000"/>
         </extensionElements>
      </sequenceFlow>
      <sequenceFlow id="sid-A692B072-7DEA-4D05-8DDD-A929F3A6D4E8" name="" sourceRef="sid-7430FB52-4AFD-4F7E-ABE4-2F2A8A733703" targetRef="sid-2630F32C-9536-4269-A7CF-561AF28EFB1E">
         <extensionElements>
            <signavio:signavioMetaData metaKey="bordercolor" metaValue="#000000"/>
         </extensionElements>
      </sequenceFlow>
      <sequenceFlow id="sid-51044AB8-126C-424D-9106-DA1C11BC2347" name="" sourceRef="sid-2630F32C-9536-4269-A7CF-561AF28EFB1E" targetRef="sid-9DFA5417-4FEC-425B-B2D1-B5F03D68678A">
         <extensionElements>
            <signavio:signavioMetaData metaKey="bordercolor" metaValue="#000000"/>
         </extensionElements>
      </sequenceFlow>
      <sequenceFlow id="sid-2696C129-64B0-4281-92F2-12B173B2BC2A" name="" sourceRef="sid-E6923AF8-3A97-40D7-B21F-3646FECB7AF8" targetRef="sid-418B38FB-7008-44FB-B9CE-120166643831">
         <extensionElements>
            <signavio:signavioMetaData metaKey="bordercolor" metaValue="#000000"/>
         </extensionElements>
      </sequenceFlow>
      <sequenceFlow id="sid-BDA672DD-C24D-42EB-857B-065844723B49" name="" sourceRef="sid-0EC2763A-9201-4614-A920-AAAEAFBE8E2C" targetRef="sid-33E456DE-CC4F-4B5A-86E7-559336AB9B89">
         <extensionElements>
            <signavio:signavioMetaData metaKey="bordercolor" metaValue="#000000"/>
         </extensionElements>
      </sequenceFlow>
      <sequenceFlow id="sid-F823339F-6F9D-452F-AB0F-4F1C2842E809" name="yes" sourceRef="sid-33E456DE-CC4F-4B5A-86E7-559336AB9B89" targetRef="sid-FD45EA49-09D1-4095-BB48-556DB1A75527">
         <extensionElements>
            <signavio:signavioMetaData metaKey="bordercolor" metaValue="#000000"/>
         </extensionElements>
      </sequenceFlow>
      <sequenceFlow id="sid-383C569E-4570-4E2A-902E-D4C779A0A947" name="" sourceRef="sid-FD45EA49-09D1-4095-BB48-556DB1A75527" targetRef="sid-DC2969BF-6A80-44FC-B3F6-036C0092F0F7">
         <extensionElements>
            <signavio:signavioMetaData metaKey="bordercolor" metaValue="#000000"/>
         </extensionElements>
      </sequenceFlow>
      <sequenceFlow id="sid-C209E9C5-4B18-4C90-AE31-B0F1B35CC5D8" name="" sourceRef="sid-DC2969BF-6A80-44FC-B3F6-036C0092F0F7" targetRef="sid-854C36B9-7E0D-448A-BC64-DDDC9D5FEFAC">
         <extensionElements>
            <signavio:signavioMetaData metaKey="bordercolor" metaValue="#000000"/>
         </extensionElements>
      </sequenceFlow>
      <sequenceFlow id="sid-208F6111-F08D-4C49-859C-48E0F4ED269F" name="" sourceRef="sid-8863F885-4FF0-4EFD-8BF3-D5065BA3B824" targetRef="sid-B59DFB83-2885-419F-ADE9-B5650C3847A5">
         <extensionElements>
            <signavio:signavioMetaData metaKey="bordercolor" metaValue="#000000"/>
         </extensionElements>
      </sequenceFlow>
      <sequenceFlow id="sid-4436D6ED-1331-4F0D-9BCF-17443A05E75D" name="no" sourceRef="sid-BD5CC168-F7DC-42B9-BEBD-A3C1DB7207F9" targetRef="sid-D6187B08-80E8-477A-92D6-530FFC6ECC63">
         <extensionElements>
            <signavio:signavioMetaData metaKey="bordercolor" metaValue="#000000"/>
         </extensionElements>
      </sequenceFlow>
      <sequenceFlow id="sid-32F5661F-AB30-4164-89C9-DB9ED760E090" name="" sourceRef="sid-5CA16D24-3FD5-4CE3-8D6C-2BBF504EAC4F" targetRef="sid-D6187B08-80E8-477A-92D6-530FFC6ECC63">
         <extensionElements>
            <signavio:signavioMetaData metaKey="bordercolor" metaValue="#000000"/>
         </extensionElements>
      </sequenceFlow>
      <sequenceFlow id="sid-54792194-1B1C-49C0-8CBB-2F48E882A1EA" name="yes" sourceRef="sid-BD5CC168-F7DC-42B9-BEBD-A3C1DB7207F9" targetRef="sid-5CA16D24-3FD5-4CE3-8D6C-2BBF504EAC4F">
         <extensionElements>
            <signavio:signavioMetaData metaKey="bordercolor" metaValue="#000000"/>
         </extensionElements>
      </sequenceFlow>
      <sequenceFlow id="sid-EC6318FE-D1FD-46D7-B5B7-7CF3DA988808" name="" sourceRef="sid-AD9D8B14-AC80-4FD4-9051-EFB6ADDD3214" targetRef="sid-8F5F2476-4EA2-495E-9757-899AAFC756FD">
         <extensionElements>
            <signavio:signavioMetaData metaKey="bordercolor" metaValue="#000000"/>
         </extensionElements>
      </sequenceFlow>
      <sequenceFlow id="sid-A800686D-D775-4420-86E7-1E531E2A9542" name="" sourceRef="sid-8F5F2476-4EA2-495E-9757-899AAFC756FD" targetRef="sid-1F486EB5-3B17-4480-9C18-69BEE45E0245">
         <extensionElements>
            <signavio:signavioMetaData metaKey="bordercolor" metaValue="#000000"/>
         </extensionElements>
      </sequenceFlow>
      <sequenceFlow id="sid-155C3758-2E71-4A7C-980C-3BF408D1F54A" name="" sourceRef="sid-1F486EB5-3B17-4480-9C18-69BEE45E0245" targetRef="sid-92EA788D-06A7-4D8E-912A-CED64ECC59D4">
         <extensionElements>
            <signavio:signavioMetaData metaKey="bordercolor" metaValue="#000000"/>
         </extensionElements>
      </sequenceFlow>
      <sequenceFlow id="sid-94A41BA6-5A67-4D8B-BB91-A04237847054" name="&gt;20" sourceRef="sid-92EA788D-06A7-4D8E-912A-CED64ECC59D4" targetRef="sid-AC7992E6-06B8-435D-9F22-60658848E4C2">
         <extensionElements>
            <signavio:signavioMetaData metaKey="bordercolor" metaValue="#000000"/>
         </extensionElements>
      </sequenceFlow>
      <sequenceFlow id="sid-883B2AC1-4FB1-435E-99DC-695C80A6703A" name="" sourceRef="sid-AC7992E6-06B8-435D-9F22-60658848E4C2" targetRef="sid-C85C7258-8C45-490E-B0BF-C495C637DF62">
         <extensionElements>
            <signavio:signavioMetaData metaKey="bordercolor" metaValue="#000000"/>
         </extensionElements>
      </sequenceFlow>
      <sequenceFlow id="sid-29674EBC-F2E6-479A-A313-56BE61C7E390" name="&lt;=20" sourceRef="sid-92EA788D-06A7-4D8E-912A-CED64ECC59D4" targetRef="sid-C85C7258-8C45-490E-B0BF-C495C637DF62">
         <extensionElements>
            <signavio:signavioMetaData metaKey="bordercolor" metaValue="#000000"/>
         </extensionElements>
      </sequenceFlow>
      <sequenceFlow id="sid-7736E86C-8EFF-4509-A98D-0F06EE0498AF" name="" sourceRef="sid-C85C7258-8C45-490E-B0BF-C495C637DF62" targetRef="sid-677CABCE-CD21-4737-9EB9-FED9D2F9F061">
         <extensionElements>
            <signavio:signavioMetaData metaKey="bordercolor" metaValue="#000000"/>
         </extensionElements>
      </sequenceFlow>
      <sequenceFlow id="sid-B30CA1EE-CF7C-40BA-A05B-A092B857D9E9" name="" sourceRef="sid-677CABCE-CD21-4737-9EB9-FED9D2F9F061" targetRef="sid-435EB1D1-786A-411B-984A-8943524F8FD5">
         <extensionElements>
            <signavio:signavioMetaData metaKey="bordercolor" metaValue="#000000"/>
         </extensionElements>
      </sequenceFlow>
      <sequenceFlow id="sid-2FBA0C62-F46C-4967-9F39-AC37E19A3CF4" name="" sourceRef="sid-13355D1A-3CAF-4D8B-9411-A88A615733C2" targetRef="sid-6E780731-665F-4684-B805-446F5BA5C7A1">
         <extensionElements>
            <signavio:signavioMetaData metaKey="bordercolor" metaValue="#000000"/>
         </extensionElements>
      </sequenceFlow>
      <sequenceFlow id="sid-1975545F-B636-4B1D-9C3D-D659AEFD7541" name="no" sourceRef="sid-435EB1D1-786A-411B-984A-8943524F8FD5" targetRef="sid-6E780731-665F-4684-B805-446F5BA5C7A1">
         <extensionElements>
            <signavio:signavioMetaData metaKey="bordercolor" metaValue="#000000"/>
         </extensionElements>
      </sequenceFlow>
      <sequenceFlow id="sid-FE70F0AD-AA74-41A2-879D-0A6B82B68D35" name="yes" sourceRef="sid-435EB1D1-786A-411B-984A-8943524F8FD5" targetRef="sid-13355D1A-3CAF-4D8B-9411-A88A615733C2">
         <extensionElements>
            <signavio:signavioMetaData metaKey="bordercolor" metaValue="#000000"/>
         </extensionElements>
      </sequenceFlow>
      <sequenceFlow id="sid-50D7AB66-0E6F-4D1B-8E28-BEDB9264FB21" name="" sourceRef="sid-6E780731-665F-4684-B805-446F5BA5C7A1" targetRef="sid-247ED8B9-DDFF-4DFC-A104-AF2CB3692A93">
         <extensionElements>
            <signavio:signavioMetaData metaKey="bordercolor" metaValue="#000000"/>
         </extensionElements>
      </sequenceFlow>
      <sequenceFlow id="sid-1BBE3964-B85A-4B0D-AE10-5767BCD9DE10" name="" sourceRef="sid-247ED8B9-DDFF-4DFC-A104-AF2CB3692A93" targetRef="sid-62948860-1F23-4957-90B8-9772DFAA3582">
         <extensionElements>
            <signavio:signavioMetaData metaKey="bordercolor" metaValue="#000000"/>
         </extensionElements>
      </sequenceFlow>
      <sequenceFlow id="sid-D99349A7-27DD-4BDC-BBB2-7EC503E56099" name="" sourceRef="sid-62948860-1F23-4957-90B8-9772DFAA3582" targetRef="sid-01E3C6E3-CD7A-4DAC-9B9D-AC030EA04370">
         <extensionElements>
            <signavio:signavioMetaData metaKey="bordercolor" metaValue="#000000"/>
         </extensionElements>
      </sequenceFlow>
      <sequenceFlow id="sid-618AFD2C-2C33-4C4E-A5FF-EC02C036EA1D" name="" sourceRef="sid-9DFA5417-4FEC-425B-B2D1-B5F03D68678A" targetRef="sid-E6923AF8-3A97-40D7-B21F-3646FECB7AF8">
         <extensionElements>
            <signavio:signavioMetaData metaKey="bordercolor" metaValue="#000000"/>
         </extensionElements>
      </sequenceFlow>
      <sequenceFlow id="sid-A9CA8785-6A01-4F96-95D3-D12C0D7B1AFA" name="" sourceRef="sid-EDBE25D0-9DBB-4CF1-9E32-2D030C43D7C2" targetRef="sid-0EC2763A-9201-4614-A920-AAAEAFBE8E2C">
         <extensionElements>
            <signavio:signavioMetaData metaKey="bordercolor" metaValue="#000000"/>
         </extensionElements>
      </sequenceFlow>
      <sequenceFlow id="sid-0B5E3CD8-AC7F-43E6-984F-FDD78F0FDA96" name="" sourceRef="sid-418B38FB-7008-44FB-B9CE-120166643831" targetRef="sid-EDBE25D0-9DBB-4CF1-9E32-2D030C43D7C2">
         <extensionElements>
            <signavio:signavioMetaData metaKey="bordercolor" metaValue="#000000"/>
         </extensionElements>
      </sequenceFlow>
      <sequenceFlow id="sid-8B6122D3-1291-4058-8E77-2406986C806C" name="" sourceRef="sid-2A51A6C7-5668-46AD-9EFE-8FFF9B5B3032" targetRef="sid-418B38FB-7008-44FB-B9CE-120166643831">
         <extensionElements>
            <signavio:signavioMetaData metaKey="bordercolor" metaValue="#000000"/>
         </extensionElements>
      </sequenceFlow>
      <sequenceFlow id="sid-6DA08284-BF0F-4A64-B9DB-9859CC72E24B" name="no" sourceRef="sid-854C36B9-7E0D-448A-BC64-DDDC9D5FEFAC" targetRef="sid-2A51A6C7-5668-46AD-9EFE-8FFF9B5B3032">
         <extensionElements>
            <signavio:signavioMetaData metaKey="bordercolor" metaValue="#000000"/>
         </extensionElements>
      </sequenceFlow>
      <sequenceFlow id="sid-6C9D0FEA-F7F5-46BA-8D6F-D2F234811F3D" name="yes" sourceRef="sid-854C36B9-7E0D-448A-BC64-DDDC9D5FEFAC" targetRef="sid-AD244CB0-E51D-45BA-ADC9-5B93EE8F48CD">
         <extensionElements>
            <signavio:signavioMetaData metaKey="bordercolor" metaValue="#000000"/>
         </extensionElements>
      </sequenceFlow>
      <sequenceFlow id="sid-A9F39EA9-A50C-4474-8BE6-26745F118C1D" name="" sourceRef="sid-AD244CB0-E51D-45BA-ADC9-5B93EE8F48CD" targetRef="sid-8863F885-4FF0-4EFD-8BF3-D5065BA3B824">
         <extensionElements>
            <signavio:signavioMetaData metaKey="bordercolor" metaValue="#000000"/>
         </extensionElements>
      </sequenceFlow>
      <sequenceFlow id="sid-155BB5ED-7CAC-4D9F-ABD1-3ED8707BA7CD" name="" sourceRef="sid-C57349ED-2135-40D6-89F3-C1DECADAE7DA" targetRef="sid-AD9D8B14-AC80-4FD4-9051-EFB6ADDD3214">
         <extensionElements>
            <signavio:signavioMetaData metaKey="bordercolor" metaValue="#000000"/>
         </extensionElements>
      </sequenceFlow>
      <sequenceFlow id="sid-A5DED093-9F99-4E3D-82F3-1F9F59A84173" name="" sourceRef="sid-B59DFB83-2885-419F-ADE9-B5650C3847A5" targetRef="sid-BD5CC168-F7DC-42B9-BEBD-A3C1DB7207F9">
         <extensionElements>
            <signavio:signavioMetaData metaKey="bordercolor" metaValue="#000000"/>
         </extensionElements>
      </sequenceFlow>
      <sequenceFlow id="sid-1D40A4AC-2144-4D89-8E4C-B86C5CEFCB8C" name="" sourceRef="sid-D6187B08-80E8-477A-92D6-530FFC6ECC63" targetRef="sid-C57349ED-2135-40D6-89F3-C1DECADAE7DA">
         <extensionElements>
            <signavio:signavioMetaData metaKey="bordercolor" metaValue="#000000"/>
         </extensionElements>
      </sequenceFlow>
      <sequenceFlow id="sid-4CC411B5-9071-4F30-A8D1-2389EAE0D1DB" name="" sourceRef="sid-36110983-BA76-479B-A292-384FAF79D0CD" targetRef="sid-AD244CB0-E51D-45BA-ADC9-5B93EE8F48CD">
         <extensionElements>
            <signavio:signavioMetaData metaKey="bordercolor" metaValue="#000000"/>
         </extensionElements>
      </sequenceFlow>
      <sequenceFlow id="sid-9F5CFF22-3AF6-4E31-9448-4E6DF3EE6076" name="no" sourceRef="sid-33E456DE-CC4F-4B5A-86E7-559336AB9B89" targetRef="sid-36110983-BA76-479B-A292-384FAF79D0CD">
         <extensionElements>
            <signavio:signavioMetaData metaKey="bordercolor" metaValue="#000000"/>
         </extensionElements>
      </sequenceFlow>
   </process>
   <bpmndi:BPMNDiagram id="sid-5e401bd5-0133-4f27-8bb6-2a454345113b">
      <bpmndi:BPMNPlane bpmnElement="sid-ddd9b946-b7fd-431a-a86e-7b465bb2b052" id="sid-72033b58-f09c-4c1b-916f-22d3b254c2e9">
         <bpmndi:BPMNShape bpmnElement="sid-2317A638-A5D2-4EC3-BE9C-E603A98B6A7F" id="sid-2317A638-A5D2-4EC3-BE9C-E603A98B6A7F_gui">
            <omgdc:Bounds height="30.0" width="30.0" x="250.0" y="250.0"/>
         </bpmndi:BPMNShape>
         <bpmndi:BPMNShape bpmnElement="sid-B8C36DE1-F2FA-43B8-8704-CB24D7F2E1FF" id="sid-B8C36DE1-F2FA-43B8-8704-CB24D7F2E1FF_gui">
            <omgdc:Bounds height="80.0" width="100.0" x="305.0" y="225.0"/>
            <bpmndi:BPMNLabel labelStyle="sid-96d60889-9658-44fb-9979-edd95e7a0725">
               <omgdc:Bounds height="24.0" width="89.4857177734375" x="310.25714111328125" y="251.0"/>
            </bpmndi:BPMNLabel>
         </bpmndi:BPMNShape>
         <bpmndi:BPMNShape bpmnElement="sid-F7E8B18F-EC6C-453D-BACE-4FB6F5D0C295" id="sid-F7E8B18F-EC6C-453D-BACE-4FB6F5D0C295_gui">
            <omgdc:Bounds height="80.0" width="100.0" x="430.0" y="225.0"/>
            <bpmndi:BPMNLabel labelStyle="sid-96d60889-9658-44fb-9979-edd95e7a0725">
               <omgdc:Bounds height="48.0" width="79.4571533203125" x="440.27142333984375" y="239.0"/>
            </bpmndi:BPMNLabel>
         </bpmndi:BPMNShape>
         <bpmndi:BPMNShape bpmnElement="sid-64704B6E-960B-4C5A-AF54-3BC1009F9D72" id="sid-64704B6E-960B-4C5A-AF54-3BC1009F9D72_gui">
            <omgdc:Bounds height="80.0" width="100.0" x="555.0" y="225.0"/>
            <bpmndi:BPMNLabel labelStyle="sid-96d60889-9658-44fb-9979-edd95e7a0725">
               <omgdc:Bounds height="60.0" width="69.42857360839844" x="570.2857131958008" y="233.0"/>
            </bpmndi:BPMNLabel>
         </bpmndi:BPMNShape>
         <bpmndi:BPMNShape bpmnElement="sid-041B38D0-8F0F-4AC5-949C-138B4093A933" id="sid-041B38D0-8F0F-4AC5-949C-138B4093A933_gui">
            <omgdc:Bounds height="80.0" width="100.0" x="680.0" y="225.0"/>
            <bpmndi:BPMNLabel labelStyle="sid-96d60889-9658-44fb-9979-edd95e7a0725">
               <omgdc:Bounds height="60.0" width="69.42857360839844" x="695.2857131958008" y="233.0"/>
            </bpmndi:BPMNLabel>
         </bpmndi:BPMNShape>
         <bpmndi:BPMNShape bpmnElement="sid-6F1893B5-6DDA-4CA6-A2C8-589FB2D85811" id="sid-6F1893B5-6DDA-4CA6-A2C8-589FB2D85811_gui">
            <omgdc:Bounds height="80.0" width="100.0" x="805.0" y="225.0"/>
            <bpmndi:BPMNLabel labelStyle="sid-96d60889-9658-44fb-9979-edd95e7a0725">
               <omgdc:Bounds height="48.0" width="74.82857513427734" x="817.5857124328613" y="239.0"/>
            </bpmndi:BPMNLabel>
         </bpmndi:BPMNShape>
         <bpmndi:BPMNShape bpmnElement="sid-7430FB52-4AFD-4F7E-ABE4-2F2A8A733703" id="sid-7430FB52-4AFD-4F7E-ABE4-2F2A8A733703_gui">
            <omgdc:Bounds height="80.0" width="100.0" x="930.0" y="225.0"/>
            <bpmndi:BPMNLabel labelStyle="sid-96d60889-9658-44fb-9979-edd95e7a0725">
               <omgdc:Bounds height="36.0" width="91.028564453125" x="934.4857177734375" y="245.0"/>
            </bpmndi:BPMNLabel>
         </bpmndi:BPMNShape>
         <bpmndi:BPMNShape bpmnElement="sid-2630F32C-9536-4269-A7CF-561AF28EFB1E" id="sid-2630F32C-9536-4269-A7CF-561AF28EFB1E_gui">
            <omgdc:Bounds height="80.0" width="100.0" x="1055.0" y="225.0"/>
            <bpmndi:BPMNLabel labelStyle="sid-96d60889-9658-44fb-9979-edd95e7a0725">
               <omgdc:Bounds height="72.0" width="91.028564453125" x="1059.4857177734375" y="227.0"/>
            </bpmndi:BPMNLabel>
         </bpmndi:BPMNShape>
         <bpmndi:BPMNShape bpmnElement="sid-E6923AF8-3A97-40D7-B21F-3646FECB7AF8" id="sid-E6923AF8-3A97-40D7-B21F-3646FECB7AF8_gui">
            <omgdc:Bounds height="80.0" width="100.0" x="1300.0" y="225.24520144388578"/>
            <bpmndi:BPMNLabel labelStyle="sid-96d60889-9658-44fb-9979-edd95e7a0725">
               <omgdc:Bounds height="72.0" width="91.028564453125" x="1304.4857177734375" y="227.24520144388578"/>
            </bpmndi:BPMNLabel>
         </bpmndi:BPMNShape>
         <bpmndi:BPMNShape bpmnElement="sid-0EC2763A-9201-4614-A920-AAAEAFBE8E2C" id="sid-0EC2763A-9201-4614-A920-AAAEAFBE8E2C_gui">
            <omgdc:Bounds height="80.0" width="100.0" x="1625.0" y="225.0"/>
            <bpmndi:BPMNLabel labelStyle="sid-96d60889-9658-44fb-9979-edd95e7a0725">
               <omgdc:Bounds height="48.0" width="91.028564453125" x="1629.4857177734375" y="239.0"/>
            </bpmndi:BPMNLabel>
         </bpmndi:BPMNShape>
         <bpmndi:BPMNShape bpmnElement="sid-33E456DE-CC4F-4B5A-86E7-559336AB9B89" id="sid-33E456DE-CC4F-4B5A-86E7-559336AB9B89_gui" isMarkerVisible="true">
            <omgdc:Bounds height="40.0" width="40.0" x="1750.0" y="245.0"/>
            <bpmndi:BPMNLabel labelStyle="sid-30d34f3d-78d9-4941-b5c2-6122e574f009">
               <omgdc:Bounds height="12.0" width="48.599998474121094" x="1745.7000007629395" y="225.0"/>
            </bpmndi:BPMNLabel>
         </bpmndi:BPMNShape>
         <bpmndi:BPMNShape bpmnElement="sid-FD45EA49-09D1-4095-BB48-556DB1A75527" id="sid-FD45EA49-09D1-4095-BB48-556DB1A75527_gui">
            <omgdc:Bounds height="80.0" width="100.0" x="1835.0" y="225.0"/>
            <bpmndi:BPMNLabel labelStyle="sid-96d60889-9658-44fb-9979-edd95e7a0725">
               <omgdc:Bounds height="48.0" width="86.39999389648438" x="1841.8000030517578" y="239.0"/>
            </bpmndi:BPMNLabel>
         </bpmndi:BPMNShape>
         <bpmndi:BPMNShape bpmnElement="sid-DC2969BF-6A80-44FC-B3F6-036C0092F0F7" id="sid-DC2969BF-6A80-44FC-B3F6-036C0092F0F7_gui">
            <omgdc:Bounds height="80.0" width="100.0" x="1960.0" y="225.0"/>
            <bpmndi:BPMNLabel labelStyle="sid-96d60889-9658-44fb-9979-edd95e7a0725">
               <omgdc:Bounds height="48.0" width="91.028564453125" x="1964.4857177734375" y="239.0"/>
            </bpmndi:BPMNLabel>
         </bpmndi:BPMNShape>
         <bpmndi:BPMNShape bpmnElement="sid-2A51A6C7-5668-46AD-9EFE-8FFF9B5B3032" id="sid-2A51A6C7-5668-46AD-9EFE-8FFF9B5B3032_gui">
            <omgdc:Bounds height="80.0" width="100.0" x="1395.0" y="140.0"/>
            <bpmndi:BPMNLabel labelStyle="sid-96d60889-9658-44fb-9979-edd95e7a0725">
               <omgdc:Bounds height="48.0" width="90.25714111328125" x="1399.8714294433594" y="154.0"/>
            </bpmndi:BPMNLabel>
         </bpmndi:BPMNShape>
         <bpmndi:BPMNShape bpmnElement="sid-8863F885-4FF0-4EFD-8BF3-D5065BA3B824" id="sid-8863F885-4FF0-4EFD-8BF3-D5065BA3B824_gui">
            <omgdc:Bounds height="80.0" width="100.0" x="2220.0" y="225.0"/>
            <bpmndi:BPMNLabel labelStyle="sid-96d60889-9658-44fb-9979-edd95e7a0725">
               <omgdc:Bounds height="48.0" width="87.17141723632812" x="2226.414291381836" y="239.0"/>
            </bpmndi:BPMNLabel>
         </bpmndi:BPMNShape>
         <bpmndi:BPMNShape bpmnElement="sid-854C36B9-7E0D-448A-BC64-DDDC9D5FEFAC" id="sid-854C36B9-7E0D-448A-BC64-DDDC9D5FEFAC_gui" isMarkerVisible="true">
            <omgdc:Bounds height="40.0" width="40.0" x="2085.0" y="245.0"/>
            <bpmndi:BPMNLabel labelStyle="sid-30d34f3d-78d9-4941-b5c2-6122e574f009">
               <omgdc:Bounds height="24.0" width="43.97142791748047" x="2083.0142860412598" y="290.0"/>
            </bpmndi:BPMNLabel>
         </bpmndi:BPMNShape>
         <bpmndi:BPMNShape bpmnElement="sid-B59DFB83-2885-419F-ADE9-B5650C3847A5" id="sid-B59DFB83-2885-419F-ADE9-B5650C3847A5_gui">
            <omgdc:Bounds height="80.0" width="100.0" x="2345.0" y="225.24520144388578"/>
            <bpmndi:BPMNLabel labelStyle="sid-96d60889-9658-44fb-9979-edd95e7a0725">
               <omgdc:Bounds height="60.0" width="85.62857055664062" x="2352.1857147216797" y="233.24520144388578"/>
            </bpmndi:BPMNLabel>
         </bpmndi:BPMNShape>
         <bpmndi:BPMNShape bpmnElement="sid-BD5CC168-F7DC-42B9-BEBD-A3C1DB7207F9" id="sid-BD5CC168-F7DC-42B9-BEBD-A3C1DB7207F9_gui" isMarkerVisible="true">
            <omgdc:Bounds height="40.0" width="40.0" x="2480.0" y="245.0"/>
            <bpmndi:BPMNLabel labelStyle="sid-30d34f3d-78d9-4941-b5c2-6122e574f009">
               <omgdc:Bounds height="12.0" width="59.400001525878906" x="2510.5" y="275.5"/>
            </bpmndi:BPMNLabel>
         </bpmndi:BPMNShape>
         <bpmndi:BPMNShape bpmnElement="sid-D6187B08-80E8-477A-92D6-530FFC6ECC63" id="sid-D6187B08-80E8-477A-92D6-530FFC6ECC63_gui" isMarkerVisible="true">
            <omgdc:Bounds height="40.0" width="40.0" x="2640.000522817578" y="245.24520144388578"/>
         </bpmndi:BPMNShape>
         <bpmndi:BPMNShape bpmnElement="sid-5CA16D24-3FD5-4CE3-8D6C-2BBF504EAC4F" id="sid-5CA16D24-3FD5-4CE3-8D6C-2BBF504EAC4F_gui">
            <omgdc:Bounds height="80.0" width="100.0" x="2532.5" y="130.0"/>
            <bpmndi:BPMNLabel labelStyle="sid-96d60889-9658-44fb-9979-edd95e7a0725">
               <omgdc:Bounds height="60.0" width="67.11428833007812" x="2548.942855834961" y="138.0"/>
            </bpmndi:BPMNLabel>
         </bpmndi:BPMNShape>
         <bpmndi:BPMNShape bpmnElement="sid-C57349ED-2135-40D6-89F3-C1DECADAE7DA" id="sid-C57349ED-2135-40D6-89F3-C1DECADAE7DA_gui">
            <omgdc:Bounds height="80.0" width="100.0" x="2710.0" y="225.0"/>
            <bpmndi:BPMNLabel labelStyle="sid-96d60889-9658-44fb-9979-edd95e7a0725">
               <omgdc:Bounds height="72.0" width="87.17141723632812" x="2716.414291381836" y="227.0"/>
            </bpmndi:BPMNLabel>
         </bpmndi:BPMNShape>
         <bpmndi:BPMNShape bpmnElement="sid-AD9D8B14-AC80-4FD4-9051-EFB6ADDD3214" id="sid-AD9D8B14-AC80-4FD4-9051-EFB6ADDD3214_gui">
            <omgdc:Bounds height="80.0" width="100.0" x="2840.0" y="225.0"/>
            <bpmndi:BPMNLabel labelStyle="sid-96d60889-9658-44fb-9979-edd95e7a0725">
               <omgdc:Bounds height="84.0" width="73.28571319580078" x="2853.3571434020996" y="221.0"/>
            </bpmndi:BPMNLabel>
         </bpmndi:BPMNShape>
         <bpmndi:BPMNShape bpmnElement="sid-8F5F2476-4EA2-495E-9757-899AAFC756FD" id="sid-8F5F2476-4EA2-495E-9757-899AAFC756FD_gui">
            <omgdc:Bounds height="80.0" width="100.0" x="2965.0" y="225.0"/>
            <bpmndi:BPMNLabel labelStyle="sid-96d60889-9658-44fb-9979-edd95e7a0725">
               <omgdc:Bounds height="48.0" width="89.4857177734375" x="2970.2571411132812" y="239.0"/>
            </bpmndi:BPMNLabel>
         </bpmndi:BPMNShape>
         <bpmndi:BPMNShape bpmnElement="sid-1F486EB5-3B17-4480-9C18-69BEE45E0245" id="sid-1F486EB5-3B17-4480-9C18-69BEE45E0245_gui">
            <omgdc:Bounds height="80.0" width="100.0" x="3090.0" y="225.0"/>
            <bpmndi:BPMNLabel labelStyle="sid-96d60889-9658-44fb-9979-edd95e7a0725">
               <omgdc:Bounds height="48.0" width="88.71429443359375" x="3095.642852783203" y="239.0"/>
            </bpmndi:BPMNLabel>
         </bpmndi:BPMNShape>
         <bpmndi:BPMNShape bpmnElement="sid-92EA788D-06A7-4D8E-912A-CED64ECC59D4" id="sid-92EA788D-06A7-4D8E-912A-CED64ECC59D4_gui" isMarkerVisible="true">
            <omgdc:Bounds height="40.0" width="40.0" x="3215.0" y="245.0"/>
            <bpmndi:BPMNLabel labelStyle="sid-30d34f3d-78d9-4941-b5c2-6122e574f009">
               <omgdc:Bounds height="12.0" width="47.82856750488281" x="3211.0857162475586" y="290.0"/>
            </bpmndi:BPMNLabel>
         </bpmndi:BPMNShape>
         <bpmndi:BPMNShape bpmnElement="sid-AC7992E6-06B8-435D-9F22-60658848E4C2" id="sid-AC7992E6-06B8-435D-9F22-60658848E4C2_gui">
            <omgdc:Bounds height="80.0" width="100.0" x="3260.0" y="140.0"/>
            <bpmndi:BPMNLabel labelStyle="sid-96d60889-9658-44fb-9979-edd95e7a0725">
               <omgdc:Bounds height="24.0" width="72.5142822265625" x="3273.7428588867188" y="166.0"/>
            </bpmndi:BPMNLabel>
         </bpmndi:BPMNShape>
         <bpmndi:BPMNShape bpmnElement="sid-C85C7258-8C45-490E-B0BF-C495C637DF62" id="sid-C85C7258-8C45-490E-B0BF-C495C637DF62_gui" isMarkerVisible="true">
            <omgdc:Bounds height="40.0" width="40.0" x="3365.0" y="245.0"/>
         </bpmndi:BPMNShape>
         <bpmndi:BPMNShape bpmnElement="sid-677CABCE-CD21-4737-9EB9-FED9D2F9F061" id="sid-677CABCE-CD21-4737-9EB9-FED9D2F9F061_gui">
            <omgdc:Bounds height="80.0" width="100.0" x="3430.0" y="225.0"/>
            <bpmndi:BPMNLabel labelStyle="sid-96d60889-9658-44fb-9979-edd95e7a0725">
               <omgdc:Bounds height="84.0" width="86.39999389648438" x="3436.800003051758" y="221.0"/>
            </bpmndi:BPMNLabel>
         </bpmndi:BPMNShape>
         <bpmndi:BPMNShape bpmnElement="sid-435EB1D1-786A-411B-984A-8943524F8FD5" id="sid-435EB1D1-786A-411B-984A-8943524F8FD5_gui" isMarkerVisible="true">
            <omgdc:Bounds height="40.0" width="40.0" x="3555.0" y="245.0"/>
            <bpmndi:BPMNLabel labelStyle="sid-30d34f3d-78d9-4941-b5c2-6122e574f009">
               <omgdc:Bounds height="36.0" width="96.42857360839844" x="3526.785713195801" y="290.0"/>
            </bpmndi:BPMNLabel>
         </bpmndi:BPMNShape>
         <bpmndi:BPMNShape bpmnElement="sid-13355D1A-3CAF-4D8B-9411-A88A615733C2" id="sid-13355D1A-3CAF-4D8B-9411-A88A615733C2_gui">
            <omgdc:Bounds height="80.0" width="100.0" x="3640.0" y="225.0"/>
            <bpmndi:BPMNLabel labelStyle="sid-96d60889-9658-44fb-9979-edd95e7a0725">
               <omgdc:Bounds height="48.0" width="60.17143249511719" x="3659.9142837524414" y="239.0"/>
            </bpmndi:BPMNLabel>
         </bpmndi:BPMNShape>
         <bpmndi:BPMNShape bpmnElement="sid-6E780731-665F-4684-B805-446F5BA5C7A1" id="sid-6E780731-665F-4684-B805-446F5BA5C7A1_gui" isMarkerVisible="true">
            <omgdc:Bounds height="40.0" width="40.0" x="3765.0" y="245.0"/>
         </bpmndi:BPMNShape>
         <bpmndi:BPMNShape bpmnElement="sid-247ED8B9-DDFF-4DFC-A104-AF2CB3692A93" id="sid-247ED8B9-DDFF-4DFC-A104-AF2CB3692A93_gui">
            <omgdc:Bounds height="80.0" width="100.0" x="3830.0" y="225.0"/>
            <bpmndi:BPMNLabel labelStyle="sid-96d60889-9658-44fb-9979-edd95e7a0725">
               <omgdc:Bounds height="48.0" width="82.5428466796875" x="3838.7285766601562" y="239.0"/>
            </bpmndi:BPMNLabel>
         </bpmndi:BPMNShape>
         <bpmndi:BPMNShape bpmnElement="sid-62948860-1F23-4957-90B8-9772DFAA3582" id="sid-62948860-1F23-4957-90B8-9772DFAA3582_gui">
            <omgdc:Bounds height="80.0" width="100.0" x="3955.0" y="225.0"/>
            <bpmndi:BPMNLabel labelStyle="sid-96d60889-9658-44fb-9979-edd95e7a0725">
               <omgdc:Bounds height="36.0" width="87.94285583496094" x="3961.0285720825195" y="245.0"/>
            </bpmndi:BPMNLabel>
         </bpmndi:BPMNShape>
         <bpmndi:BPMNShape bpmnElement="sid-01E3C6E3-CD7A-4DAC-9B9D-AC030EA04370" id="sid-01E3C6E3-CD7A-4DAC-9B9D-AC030EA04370_gui">
            <omgdc:Bounds height="28.0" width="28.0" x="4080.0" y="251.0"/>
         </bpmndi:BPMNShape>
         <bpmndi:BPMNShape bpmnElement="sid-9DFA5417-4FEC-425B-B2D1-B5F03D68678A" id="sid-9DFA5417-4FEC-425B-B2D1-B5F03D68678A_gui">
            <omgdc:Bounds height="80.0" width="100.0" x="1175.0" y="225.0"/>
            <bpmndi:BPMNLabel labelStyle="sid-96d60889-9658-44fb-9979-edd95e7a0725">
               <omgdc:Bounds height="48.0" width="83.31428527832031" x="1183.3428573608398" y="239.0"/>
            </bpmndi:BPMNLabel>
         </bpmndi:BPMNShape>
         <bpmndi:BPMNShape bpmnElement="sid-EDBE25D0-9DBB-4CF1-9E32-2D030C43D7C2" id="sid-EDBE25D0-9DBB-4CF1-9E32-2D030C43D7C2_gui">
            <omgdc:Bounds height="80.0" width="100.0" x="1490.0" y="225.24520144388578"/>
            <bpmndi:BPMNLabel labelStyle="sid-96d60889-9658-44fb-9979-edd95e7a0725">
               <omgdc:Bounds height="60.0" width="64.80000305175781" x="1507.599998474121" y="233.24520144388578"/>
            </bpmndi:BPMNLabel>
         </bpmndi:BPMNShape>
         <bpmndi:BPMNShape bpmnElement="sid-418B38FB-7008-44FB-B9CE-120166643831" id="sid-418B38FB-7008-44FB-B9CE-120166643831_gui" isMarkerVisible="true">
            <omgdc:Bounds height="40.0" width="40.0" x="1425.0" y="245.24520144388578"/>
         </bpmndi:BPMNShape>
         <bpmndi:BPMNShape bpmnElement="sid-36110983-BA76-479B-A292-384FAF79D0CD" id="sid-36110983-BA76-479B-A292-384FAF79D0CD_gui">
            <omgdc:Bounds height="80.0" width="100.0" x="1835.0" y="310.0"/>
            <bpmndi:BPMNLabel labelStyle="sid-96d60889-9658-44fb-9979-edd95e7a0725">
               <omgdc:Bounds height="36.0" width="87.94285583496094" x="1841.0285720825195" y="330.0"/>
            </bpmndi:BPMNLabel>
         </bpmndi:BPMNShape>
         <bpmndi:BPMNShape bpmnElement="sid-AD244CB0-E51D-45BA-ADC9-5B93EE8F48CD" id="sid-AD244CB0-E51D-45BA-ADC9-5B93EE8F48CD_gui" isMarkerVisible="true">
            <omgdc:Bounds height="40.0" width="40.0" x="2150.0" y="245.0"/>
         </bpmndi:BPMNShape>
         <bpmndi:BPMNEdge bpmnElement="sid-F48E8617-4FDE-42AD-B676-E8863D057646" id="sid-F48E8617-4FDE-42AD-B676-E8863D057646_gui">
            <omgdi:waypoint x="280.0" y="265.0"/>
            <omgdi:waypoint x="305.0" y="265.0"/>
         </bpmndi:BPMNEdge>
         <bpmndi:BPMNEdge bpmnElement="sid-FFED330A-0D57-4CE2-B13E-0E3292D2B364" id="sid-FFED330A-0D57-4CE2-B13E-0E3292D2B364_gui">
            <omgdi:waypoint x="405.0" y="265.0"/>
            <omgdi:waypoint x="430.0" y="265.0"/>
         </bpmndi:BPMNEdge>
         <bpmndi:BPMNEdge bpmnElement="sid-E305139C-C162-46AC-8C78-BEC440359105" id="sid-E305139C-C162-46AC-8C78-BEC440359105_gui">
            <omgdi:waypoint x="530.0" y="265.0"/>
            <omgdi:waypoint x="555.0" y="265.0"/>
         </bpmndi:BPMNEdge>
         <bpmndi:BPMNEdge bpmnElement="sid-C9393AA4-5750-48C0-A207-0B1DAE9DD0F2" id="sid-C9393AA4-5750-48C0-A207-0B1DAE9DD0F2_gui">
            <omgdi:waypoint x="655.0" y="265.0"/>
            <omgdi:waypoint x="680.0" y="265.0"/>
         </bpmndi:BPMNEdge>
         <bpmndi:BPMNEdge bpmnElement="sid-F9D455C9-F21B-4A1A-BF41-5E5177E6EA15" id="sid-F9D455C9-F21B-4A1A-BF41-5E5177E6EA15_gui">
            <omgdi:waypoint x="780.0" y="265.0"/>
            <omgdi:waypoint x="805.0" y="265.0"/>
         </bpmndi:BPMNEdge>
         <bpmndi:BPMNEdge bpmnElement="sid-6D656B05-27B8-406F-9D0B-AE44347CF573" id="sid-6D656B05-27B8-406F-9D0B-AE44347CF573_gui">
            <omgdi:waypoint x="905.0" y="265.0"/>
            <omgdi:waypoint x="930.0" y="265.0"/>
         </bpmndi:BPMNEdge>
         <bpmndi:BPMNEdge bpmnElement="sid-A692B072-7DEA-4D05-8DDD-A929F3A6D4E8" id="sid-A692B072-7DEA-4D05-8DDD-A929F3A6D4E8_gui">
            <omgdi:waypoint x="1030.0" y="265.0"/>
            <omgdi:waypoint x="1055.0" y="265.0"/>
         </bpmndi:BPMNEdge>
         <bpmndi:BPMNEdge bpmnElement="sid-51044AB8-126C-424D-9106-DA1C11BC2347" id="sid-51044AB8-126C-424D-9106-DA1C11BC2347_gui">
            <omgdi:waypoint x="1155.0" y="265.0"/>
            <omgdi:waypoint x="1175.0" y="265.0"/>
         </bpmndi:BPMNEdge>
         <bpmndi:BPMNEdge bpmnElement="sid-2696C129-64B0-4281-92F2-12B173B2BC2A" id="sid-2696C129-64B0-4281-92F2-12B173B2BC2A_gui">
            <omgdi:waypoint x="1400.0" y="265.5069815485978"/>
            <omgdi:waypoint x="1425.0" y="265.6378716009538"/>
         </bpmndi:BPMNEdge>
         <bpmndi:BPMNEdge bpmnElement="sid-BDA672DD-C24D-42EB-857B-065844723B49" id="sid-BDA672DD-C24D-42EB-857B-065844723B49_gui">
            <omgdi:waypoint x="1725.0" y="265.26178010471205"/>
            <omgdi:waypoint x="1750.0" y="265.39267015706804"/>
         </bpmndi:BPMNEdge>
         <bpmndi:BPMNEdge bpmnElement="sid-F823339F-6F9D-452F-AB0F-4F1C2842E809" id="sid-F823339F-6F9D-452F-AB0F-4F1C2842E809_gui">
            <omgdi:waypoint x="1790.0" y="265.414847161572"/>
            <omgdi:waypoint x="1835.0" y="265.2183406113537"/>
            <bpmndi:BPMNLabel labelStyle="sid-30d34f3d-78d9-4941-b5c2-6122e574f009">
               <omgdc:Bounds height="12.080728308051874" width="18.566503786249086" x="1797.8315381160476" y="245.29942617016533"/>
            </bpmndi:BPMNLabel>
         </bpmndi:BPMNEdge>
         <bpmndi:BPMNEdge bpmnElement="sid-383C569E-4570-4E2A-902E-D4C779A0A947" id="sid-383C569E-4570-4E2A-902E-D4C779A0A947_gui">
            <omgdi:waypoint x="1935.0" y="265.0"/>
            <omgdi:waypoint x="1960.0" y="265.0"/>
         </bpmndi:BPMNEdge>
         <bpmndi:BPMNEdge bpmnElement="sid-C209E9C5-4B18-4C90-AE31-B0F1B35CC5D8" id="sid-C209E9C5-4B18-4C90-AE31-B0F1B35CC5D8_gui">
            <omgdi:waypoint x="2060.0" y="265.26178010471205"/>
            <omgdi:waypoint x="2085.0" y="265.39267015706804"/>
         </bpmndi:BPMNEdge>
         <bpmndi:BPMNEdge bpmnElement="sid-208F6111-F08D-4C49-859C-48E0F4ED269F" id="sid-208F6111-F08D-4C49-859C-48E0F4ED269F_gui">
            <omgdi:waypoint x="2320.0" y="265.0980805775543"/>
            <omgdi:waypoint x="2345.0" y="265.1471208663315"/>
         </bpmndi:BPMNEdge>
         <bpmndi:BPMNEdge bpmnElement="sid-4436D6ED-1331-4F0D-9BCF-17443A05E75D" id="sid-4436D6ED-1331-4F0D-9BCF-17443A05E75D_gui">
            <omgdi:waypoint x="2520.0" y="265.5298838283249"/>
            <omgdi:waypoint x="2640.000522817578" y="265.7137851115442"/>
            <bpmndi:BPMNLabel labelStyle="sid-30d34f3d-78d9-4941-b5c2-6122e574f009">
               <omgdc:Bounds height="12.021264176251378" width="13.9041144717703" x="2527.982220122674" y="245.54228102642426"/>
            </bpmndi:BPMNLabel>
         </bpmndi:BPMNEdge>
         <bpmndi:BPMNEdge bpmnElement="sid-32F5661F-AB30-4164-89C9-DB9ED760E090" id="sid-32F5661F-AB30-4164-89C9-DB9ED760E090_gui">
            <omgdi:waypoint x="2632.5" y="170.0"/>
            <omgdi:waypoint x="2660.500522817578" y="170.0"/>
            <omgdi:waypoint x="2660.500522817578" y="245.24520144388578"/>
         </bpmndi:BPMNEdge>
         <bpmndi:BPMNEdge bpmnElement="sid-54792194-1B1C-49C0-8CBB-2F48E882A1EA" id="sid-54792194-1B1C-49C0-8CBB-2F48E882A1EA_gui">
            <omgdi:waypoint x="2500.5" y="245.0"/>
            <omgdi:waypoint x="2500.5" y="170.0"/>
            <omgdi:waypoint x="2532.5" y="170.0"/>
            <bpmndi:BPMNLabel labelStyle="sid-30d34f3d-78d9-4941-b5c2-6122e574f009">
               <omgdc:Bounds height="18.514404296875" width="12.0" x="2480.5" y="218.485595703125"/>
            </bpmndi:BPMNLabel>
         </bpmndi:BPMNEdge>
         <bpmndi:BPMNEdge bpmnElement="sid-EC6318FE-D1FD-46D7-B5B7-7CF3DA988808" id="sid-EC6318FE-D1FD-46D7-B5B7-7CF3DA988808_gui">
            <omgdi:waypoint x="2940.0" y="265.0"/>
            <omgdi:waypoint x="2965.0" y="265.0"/>
         </bpmndi:BPMNEdge>
         <bpmndi:BPMNEdge bpmnElement="sid-A800686D-D775-4420-86E7-1E531E2A9542" id="sid-A800686D-D775-4420-86E7-1E531E2A9542_gui">
            <omgdi:waypoint x="3065.0" y="265.0"/>
            <omgdi:waypoint x="3090.0" y="265.0"/>
         </bpmndi:BPMNEdge>
         <bpmndi:BPMNEdge bpmnElement="sid-155C3758-2E71-4A7C-980C-3BF408D1F54A" id="sid-155C3758-2E71-4A7C-980C-3BF408D1F54A_gui">
            <omgdi:waypoint x="3190.0" y="265.26178010471205"/>
            <omgdi:waypoint x="3215.0" y="265.39267015706804"/>
         </bpmndi:BPMNEdge>
         <bpmndi:BPMNEdge bpmnElement="sid-94A41BA6-5A67-4D8B-BB91-A04237847054" id="sid-94A41BA6-5A67-4D8B-BB91-A04237847054_gui">
            <omgdi:waypoint x="3235.5" y="245.0"/>
            <omgdi:waypoint x="3235.5" y="180.0"/>
            <omgdi:waypoint x="3260.0" y="180.0"/>
            <bpmndi:BPMNLabel labelStyle="sid-30d34f3d-78d9-4941-b5c2-6122e574f009">
               <omgdc:Bounds height="22.371337890625" width="12.0" x="3215.5" y="214.628662109375"/>
            </bpmndi:BPMNLabel>
         </bpmndi:BPMNEdge>
         <bpmndi:BPMNEdge bpmnElement="sid-883B2AC1-4FB1-435E-99DC-695C80A6703A" id="sid-883B2AC1-4FB1-435E-99DC-695C80A6703A_gui">
            <omgdi:waypoint x="3360.0" y="180.0"/>
            <omgdi:waypoint x="3385.5" y="180.0"/>
            <omgdi:waypoint x="3385.5" y="245.0"/>
         </bpmndi:BPMNEdge>
         <bpmndi:BPMNEdge bpmnElement="sid-29674EBC-F2E6-479A-A313-56BE61C7E390" id="sid-29674EBC-F2E6-479A-A313-56BE61C7E390_gui">
            <omgdi:waypoint x="3255.0" y="265.0"/>
            <omgdi:waypoint x="3365.0" y="265.0"/>
            <bpmndi:BPMNLabel labelStyle="sid-30d34f3d-78d9-4941-b5c2-6122e574f009">
               <omgdc:Bounds height="12.0" width="30.857177734375" x="3262.52392578125" y="245.0"/>
            </bpmndi:BPMNLabel>
         </bpmndi:BPMNEdge>
         <bpmndi:BPMNEdge bpmnElement="sid-7736E86C-8EFF-4509-A98D-0F06EE0498AF" id="sid-7736E86C-8EFF-4509-A98D-0F06EE0498AF_gui">
            <omgdi:waypoint x="3405.0" y="265.3968253968254"/>
            <omgdi:waypoint x="3430.0" y="265.2645502645503"/>
         </bpmndi:BPMNEdge>
         <bpmndi:BPMNEdge bpmnElement="sid-B30CA1EE-CF7C-40BA-A05B-A092B857D9E9" id="sid-B30CA1EE-CF7C-40BA-A05B-A092B857D9E9_gui">
            <omgdi:waypoint x="3530.0" y="265.26178010471205"/>
            <omgdi:waypoint x="3555.0" y="265.39267015706804"/>
         </bpmndi:BPMNEdge>
         <bpmndi:BPMNEdge bpmnElement="sid-2FBA0C62-F46C-4967-9F39-AC37E19A3CF4" id="sid-2FBA0C62-F46C-4967-9F39-AC37E19A3CF4_gui">
            <omgdi:waypoint x="3740.0" y="265.26178010471205"/>
            <omgdi:waypoint x="3765.0" y="265.39267015706804"/>
         </bpmndi:BPMNEdge>
         <bpmndi:BPMNEdge bpmnElement="sid-1975545F-B636-4B1D-9C3D-D659AEFD7541" id="sid-1975545F-B636-4B1D-9C3D-D659AEFD7541_gui">
            <omgdi:waypoint x="3575.5" y="245.0"/>
            <omgdi:waypoint x="3575.5" y="172.0"/>
            <omgdi:waypoint x="3785.5" y="172.0"/>
            <omgdi:waypoint x="3785.5" y="245.0"/>
            <bpmndi:BPMNLabel labelStyle="sid-30d34f3d-78d9-4941-b5c2-6122e574f009">
               <omgdc:Bounds height="13.8857421875" width="12.0" x="3555.5" y="223.1142578125"/>
            </bpmndi:BPMNLabel>
         </bpmndi:BPMNEdge>
         <bpmndi:BPMNEdge bpmnElement="sid-FE70F0AD-AA74-41A2-879D-0A6B82B68D35" id="sid-FE70F0AD-AA74-41A2-879D-0A6B82B68D35_gui">
            <omgdi:waypoint x="3595.0" y="265.414847161572"/>
            <omgdi:waypoint x="3640.0" y="265.2183406113537"/>
            <bpmndi:BPMNLabel labelStyle="sid-30d34f3d-78d9-4941-b5c2-6122e574f009">
               <omgdc:Bounds height="12.0807288410725" width="18.566625855397433" x="3602.831538116048" y="245.2994256371447"/>
            </bpmndi:BPMNLabel>
         </bpmndi:BPMNEdge>
         <bpmndi:BPMNEdge bpmnElement="sid-50D7AB66-0E6F-4D1B-8E28-BEDB9264FB21" id="sid-50D7AB66-0E6F-4D1B-8E28-BEDB9264FB21_gui">
            <omgdi:waypoint x="3805.0" y="265.3968253968254"/>
            <omgdi:waypoint x="3830.0" y="265.2645502645503"/>
         </bpmndi:BPMNEdge>
         <bpmndi:BPMNEdge bpmnElement="sid-1BBE3964-B85A-4B0D-AE10-5767BCD9DE10" id="sid-1BBE3964-B85A-4B0D-AE10-5767BCD9DE10_gui">
            <omgdi:waypoint x="3930.0" y="265.0"/>
            <omgdi:waypoint x="3955.0" y="265.0"/>
         </bpmndi:BPMNEdge>
         <bpmndi:BPMNEdge bpmnElement="sid-D99349A7-27DD-4BDC-BBB2-7EC503E56099" id="sid-D99349A7-27DD-4BDC-BBB2-7EC503E56099_gui">
            <omgdi:waypoint x="4055.0" y="265.0"/>
            <omgdi:waypoint x="4080.0" y="265.0"/>
         </bpmndi:BPMNEdge>
         <bpmndi:BPMNEdge bpmnElement="sid-618AFD2C-2C33-4C4E-A5FF-EC02C036EA1D" id="sid-618AFD2C-2C33-4C4E-A5FF-EC02C036EA1D_gui">
            <omgdi:waypoint x="1275.0" y="265.0980805775543"/>
            <omgdi:waypoint x="1300.0" y="265.1471208663315"/>
         </bpmndi:BPMNEdge>
         <bpmndi:BPMNEdge bpmnElement="sid-A9CA8785-6A01-4F96-95D3-D12C0D7B1AFA" id="sid-A9CA8785-6A01-4F96-95D3-D12C0D7B1AFA_gui">
            <omgdi:waypoint x="1590.0" y="265.15438609429845"/>
            <omgdi:waypoint x="1625.0" y="265.09081534958733"/>
         </bpmndi:BPMNEdge>
         <bpmndi:BPMNEdge bpmnElement="sid-0B5E3CD8-AC7F-43E6-984F-FDD78F0FDA96" id="sid-0B5E3CD8-AC7F-43E6-984F-FDD78F0FDA96_gui">
            <omgdi:waypoint x="1465.0" y="265.6420268407112"/>
            <omgdi:waypoint x="1490.0" y="265.50975170843606"/>
         </bpmndi:BPMNEdge>
         <bpmndi:BPMNEdge bpmnElement="sid-8B6122D3-1291-4058-8E77-2406986C806C" id="sid-8B6122D3-1291-4058-8E77-2406986C806C_gui">
            <omgdi:waypoint x="1445.2332492041912" y="220.0"/>
            <omgdi:waypoint x="1445.380459782852" y="245.24520144388578"/>
         </bpmndi:BPMNEdge>
         <bpmndi:BPMNEdge bpmnElement="sid-6DA08284-BF0F-4A64-B9DB-9859CC72E24B" id="sid-6DA08284-BF0F-4A64-B9DB-9859CC72E24B_gui">
            <omgdi:waypoint x="2105.5" y="245.0"/>
            <omgdi:waypoint x="2105.5" y="180.0"/>
            <omgdi:waypoint x="1495.0" y="180.0"/>
            <bpmndi:BPMNLabel labelStyle="sid-30d34f3d-78d9-4941-b5c2-6122e574f009">
               <omgdc:Bounds height="13.8857421875" width="12.0" x="2085.5" y="223.1142578125"/>
            </bpmndi:BPMNLabel>
         </bpmndi:BPMNEdge>
         <bpmndi:BPMNEdge bpmnElement="sid-6C9D0FEA-F7F5-46BA-8D6F-D2F234811F3D" id="sid-6C9D0FEA-F7F5-46BA-8D6F-D2F234811F3D_gui">
            <omgdi:waypoint x="2125.0" y="265.1526717557252"/>
            <omgdi:waypoint x="2150.0" y="265.3435114503817"/>
            <bpmndi:BPMNLabel labelStyle="sid-30d34f3d-78d9-4941-b5c2-6122e574f009">
               <omgdc:Bounds height="12.140982119585573" width="18.60546818291141" x="2132.7278290372724" y="245.2116439441181"/>
            </bpmndi:BPMNLabel>
         </bpmndi:BPMNEdge>
         <bpmndi:BPMNEdge bpmnElement="sid-A9F39EA9-A50C-4474-8BE6-26745F118C1D" id="sid-A9F39EA9-A50C-4474-8BE6-26745F118C1D_gui">
            <omgdi:waypoint x="2190.0" y="265.40201005025125"/>
            <omgdi:waypoint x="2220.0" y="265.25125628140705"/>
         </bpmndi:BPMNEdge>
         <bpmndi:BPMNEdge bpmnElement="sid-155BB5ED-7CAC-4D9F-ABD1-3ED8707BA7CD" id="sid-155BB5ED-7CAC-4D9F-ABD1-3ED8707BA7CD_gui">
            <omgdi:waypoint x="2810.0" y="265.0"/>
            <omgdi:waypoint x="2840.0" y="265.0"/>
         </bpmndi:BPMNEdge>
         <bpmndi:BPMNEdge bpmnElement="sid-A5DED093-9F99-4E3D-82F3-1F9F59A84173" id="sid-A5DED093-9F99-4E3D-82F3-1F9F59A84173_gui">
            <omgdi:waypoint x="2445.0" y="265.3659590534186"/>
            <omgdi:waypoint x="2480.0" y="265.45048938009154"/>
         </bpmndi:BPMNEdge>
         <bpmndi:BPMNEdge bpmnElement="sid-1D40A4AC-2144-4D89-8E4C-B86C5CEFCB8C" id="sid-1D40A4AC-2144-4D89-8E4C-B86C5CEFCB8C_gui">
            <omgdi:waypoint x="2680.000522817578" y="265.59915617242035"/>
            <omgdi:waypoint x="2710.0" y="265.3744750550395"/>
         </bpmndi:BPMNEdge>
         <bpmndi:BPMNEdge bpmnElement="sid-4CC411B5-9071-4F30-A8D1-2389EAE0D1DB" id="sid-4CC411B5-9071-4F30-A8D1-2389EAE0D1DB_gui">
            <omgdi:waypoint x="1935.0" y="350.0"/>
            <omgdi:waypoint x="2170.5" y="350.0"/>
            <omgdi:waypoint x="2170.5" y="285.0"/>
         </bpmndi:BPMNEdge>
         <bpmndi:BPMNEdge bpmnElement="sid-9F5CFF22-3AF6-4E31-9448-4E6DF3EE6076" id="sid-9F5CFF22-3AF6-4E31-9448-4E6DF3EE6076_gui">
            <omgdi:waypoint x="1770.5" y="285.0"/>
            <omgdi:waypoint x="1770.5" y="350.0"/>
            <omgdi:waypoint x="1835.0" y="350.0"/>
            <bpmndi:BPMNLabel labelStyle="sid-30d34f3d-78d9-4941-b5c2-6122e574f009">
               <omgdc:Bounds height="13.8857421875" width="12.0" x="1750.5" y="293.0"/>
            </bpmndi:BPMNLabel>
         </bpmndi:BPMNEdge>
      </bpmndi:BPMNPlane>
      <bpmndi:BPMNLabelStyle id="sid-30d34f3d-78d9-4941-b5c2-6122e574f009">
         <omgdc:Font isBold="false" isItalic="false" isStrikeThrough="false" isUnderline="false" name="Arial" size="11.0"/>
      </bpmndi:BPMNLabelStyle>
      <bpmndi:BPMNLabelStyle id="sid-96d60889-9658-44fb-9979-edd95e7a0725">
         <omgdc:Font isBold="false" isItalic="false" isStrikeThrough="false" isUnderline="false" name="Arial" size="12.0"/>
      </bpmndi:BPMNLabelStyle>
   </bpmndi:BPMNDiagram>
</definitions>
